{
    "pageid": 1721598,
    "ns": 0,
    "type": "item",
    "id": "Q1790065",
    "claims": {
        "P41": [
            {
                "value": "Bandeira mato verde.jpg",
                "type": "string"
            }
        ],
        "P625": [
            {
                "value": {
                    "latitude": -15.396944444444,
                    "longitude": -42.865833333333,
                    "altitude": null,
                    "precision": 0.00027777777777778,
                    "globe": "http://www.wikidata.org/entity/Q2"
                },
                "type": "globecoordinate"
            },
            {
                "value": {
                    "latitude": -15.42884,
                    "longitude": -42.87463,
                    "altitude": null,
                    "precision": 1.0e-5,
                    "globe": "http://www.wikidata.org/entity/Q2"
                },
                "type": "globecoordinate"
            }
        ],
        "P17": [
            {
                "value": {
                    "entity-type": "item",
                    "numeric-id": 155,
                    "id": "Q155"
                },
                "type": "wikibase-entityid"
            }
        ],
        "P131": [
            {
                "value": {
                    "entity-type": "item",
                    "numeric-id": 39109,
                    "id": "Q39109"
                },
                "type": "wikibase-entityid"
            }
        ],
        "P31": [
            {
                "value": {
                    "entity-type": "item",
                    "numeric-id": 3184121,
                    "id": "Q3184121"
                },
                "type": "wikibase-entityid"
            }
        ],
        "P646": [
            {
                "value": "/m/043qwlp",
                "type": "string"
            }
        ],
        "P1566": [
            {
                "value": "3457398",
                "type": "string"
            },
            {
                "value": "6321558",
                "type": "string"
            }
        ],
        "P373": [
            {
                "value": "Mato Verde",
                "type": "string"
            }
        ],
        "P1667": [
            {
                "value": "1022073",
                "type": "string"
            }
        ],
        "P1585": [
            {
                "value": "3141009",
                "type": "string"
            }
        ],
        "P1082": [
            {
                "value": {
                    "amount": "+12684",
                    "unit": "1"
                },
                "type": "quantity"
            }
        ],
        "P242": [
            {
                "value": "MinasGerais Municip MatoVerde.svg",
                "type": "string"
            }
        ],
        "P94": [
            {
                "value": "Brasao mato verde.png",
                "type": "string"
            }
        ],
        "P18": [
            {
                "value": "Mato Verde.jpg",
                "type": "string"
            }
        ],
        "P910": [
            {
                "value": {
                    "entity-type": "item",
                    "numeric-id": 27499968,
                    "id": "Q27499968"
                },
                "type": "wikibase-entityid"
            }
        ],
        "P2044": [
            {
                "value": {
                    "amount": "+501",
                    "unit": "http://www.wikidata.org/entity/Q11573"
                },
                "type": "quantity"
            },
            {
                "value": {
                    "amount": "+552",
                    "unit": "http://www.wikidata.org/entity/Q11573"
                },
                "type": "quantity"
            }
        ],
        "P2046": [
            {
                "value": {
                    "amount": "+474.446",
                    "unit": "http://www.wikidata.org/entity/Q712226"
                },
                "type": "quantity"
            }
        ],
        "P1081": [
            {
                "value": {
                    "amount": "+0.662",
                    "unit": "1"
                },
                "type": "quantity"
            }
        ],
        "P47": [
            {
                "value": {
                    "entity-type": "item",
                    "numeric-id": 1790247,
                    "id": "Q1790247"
                },
                "type": "wikibase-entityid"
            },
            {
                "value": {
                    "entity-type": "item",
                    "numeric-id": 1789713,
                    "id": "Q1789713"
                },
                "type": "wikibase-entityid"
            },
            {
                "value": {
                    "entity-type": "item",
                    "numeric-id": 1789409,
                    "id": "Q1789409"
                },
                "type": "wikibase-entityid"
            }
        ],
        "P402": [
            {
                "value": "315286",
                "type": "string"
            }
        ]
    }
}