{"entities":{"Q926662":{"pageid":877043,"ns":0,"title":"Q926662","lastrevid":681880074,"modified":"2018-05-20T06:27:27Z","type":"item","id":"Q926662","labels":{"pt":{"language":"pt","value":"Itapecerica da Serra"},"eo":{"language":"eo","value":"Itapecerica da Serra"},"pl":{"language":"pl","value":"Itapecerica da Serra"},"fr":{"language":"fr","value":"Itapecerica da Serra"},"ru":{"language":"ru","value":"\u0418\u0442\u0430\u043f\u0435\u0441\u0435\u0440\u0438\u043a\u0430-\u0434\u0430-\u0421\u0435\u0440\u0440\u0430"},"es":{"language":"es","value":"Itapecerica da Serra"},"vo":{"language":"vo","value":"Itapecerica da Serra"},"en":{"language":"en","value":"Itapecerica da Serra"},"ro":{"language":"ro","value":"Itapecerica da Serra"},"uk":{"language":"uk","value":"\u0406\u0442\u0430\u043f\u0435\u0441\u0435\u0440\u0456\u043a\u0430-\u0434\u0430-\u0421\u0435\u0440\u0440\u0430"},"it":{"language":"it","value":"Itapecerica da Serra"},"mg":{"language":"mg","value":"Itapecerica da Serra"},"de":{"language":"de","value":"Itapecerica da Serra"},"war":{"language":"war","value":"Itapecerica da Serra"},"vi":{"language":"vi","value":"Itapecerica da Serra"},"bpy":{"language":"bpy","value":"\u0987\u099f\u09be\u09aa\u09c7\u09b8\u09c7\u09b0\u09bf\u0995\u09be \u09a1\u09be \u09b8\u09c7\u09b0\u09cd\u09b0\u09be"},"nl":{"language":"nl","value":"Itapecerica da Serra"},"sv":{"language":"sv","value":"Itapecerica da Serra"},"kk-arab":{"language":"kk-arab","value":"\u0649\u064a\u062a\u0627\u067e\u06d5\u0633\u06d5\u0631\u0649\u064a\u0643\u0627-\u062f\u0627-\u0633\u06d5\u0631\u0631\u0627"},"kk-cyrl":{"language":"kk-cyrl","value":"\u0418\u0442\u0430\u043f\u0435\u0441\u0435\u0440\u0438\u043a\u0430-\u0434\u0430-\u0421\u0435\u0440\u0440\u0430"},"kk-latn":{"language":"kk-latn","value":"\u00cftapeser\u00efka-da-Serra"},"nb":{"language":"nb","value":"Itapecerica da Serra"},"zh":{"language":"zh","value":"\u4f0a\u5854\u4f69\u585e\u91cc\u5361-\u8fbe\u585e\u62c9"},"kk":{"language":"kk","value":"\u0418\u0442\u0430\u043f\u0435\u0441\u0435\u0440\u0438\u043a\u0430-\u0434\u0430-\u0421\u0435\u0440\u0440\u0430"},"ceb":{"language":"ceb","value":"Itapecerica da Serra (lungsod)"},"nan":{"language":"nan","value":"Itapecerica da Serra"},"ja":{"language":"ja","value":"\u30a4\u30bf\u30da\u30bc\u30ea\u30ab\u30fb\u30c0\u30fb\u30bb\u30c3\u30e9"},"eu":{"language":"eu","value":"Itapecerica da Serra"},"ko":{"language":"ko","value":"\uc774\ud0c0\ud398\uc138\ub9ac\uce74 \ub2e4 \uc138\ub77c"},"hi":{"language":"hi","value":"\u0908\u0924\u092a\u0938\u093f\u0930\u0940\u0915\u093e \u0926\u093e \u0938\u0947\u0930\u0930"},"ar":{"language":"ar","value":"\u0625\u062a\u0627\u0628\u064a\u0633\u064a\u0631\u064a\u0643\u0627 \u062f\u0627 \u0633\u064a\u0631\u0627"},"da":{"language":"da","value":"Itapecerica da Serra"},"fi":{"language":"fi","value":"Itapecerica da Serra"},"tr":{"language":"tr","value":"Itapecerica da Serra"},"ms":{"language":"ms","value":"Itapecerica da Serra"},"id":{"language":"id","value":"Itapecerica da Serra"},"th":{"language":"th","value":"\u0e2d\u0e34\u0e15\u0e32\u0e40\u0e1b\u0e40\u0e0b\u0e23\u0e34\u0e01\u0e32 \u0e14\u0e32 \u0e40\u0e0b\u0e23\u0e32"},"ta":{"language":"ta","value":"\u0b87\u0b9f\u0baa\u0bcd\u0baa\u0bc7\u0b9a\u0bbf\u0bb0\u0bbf\u0b95\u0bcd\u0b95\u0bbe  \u0b9f\u0bbe \u0b9a\u0bc6\u0bb0\u0bcd\u0bb0\u0bbe"},"mr":{"language":"mr","value":"\u0906\u092f\u091f\u093e\u092a\u0947\u0938\u0947\u0930\u0940\u0915\u093e \u0926\u093e \u0938\u0947\u0930\u093e"},"te":{"language":"te","value":"\u0c08\u0c24\u0c2a\u0c38\u0c3f\u0c30\u0c3f\u0c15\u0c3e \u0c26\u0c3e \u0c38\u0c46\u0c30\u0c4d\u0c30\u0c3e"},"bn":{"language":"bn","value":"\u0987\u09a4\u09be\u09be\u09aa\u09c7\u09b8\u09c7\u09b0\u09bf\u0995\u09be \u09a6\u09be \u09b8\u09c7\u09b0\u200d\u09cd\u09af\u09be"},"ur":{"language":"ur","value":"\u0627\u062a\u0627\u067e\u06cc\u06a9\u06cc\u0631\u06cc\u06a9\u0627 \u062f\u0627 \u0633\u0631\u0627"},"el":{"language":"el","value":"\u0399\u03c4\u03b1\u03c0\u03b5\u03ba\u03b5\u03c1\u03af\u03ba\u03b1 \u03bd\u03c4\u03b1 \u03a3\u03ad\u03c1\u03b1"},"si":{"language":"si","value":"\u0d89\u0da7\u0db4\u0dd9\u0dc3\u0dd9\u0dbb\u0dd2\u0d9a\u0dcf \u0da9\u0dcf \u0dc3\u0dd9\u0dbb\u0dcf"},"gu":{"language":"gu","value":"\u0a87\u0a9f\u0abe\u0aaa\u0ac7\u0ab8\u0ac7\u0ab0\u0abf\u0a95\u0abe \u0aa6\u0abe \u0ab8\u0ac7\u0ab0\u0abe"},"kn":{"language":"kn","value":"\u0c87\u0c9f\u0cbe\u0caa\u0cc6\u0cb8\u0cc6\u0cb0\u0cbf\u0c95\u0cbe \u0ca1\u0cbe \u0cb8\u0cb0\u0ccd\u0cb0\u0cbe"},"lt":{"language":"lt","value":"Itapekerika se Sera"},"hu":{"language":"hu","value":"Itapecerica da Serra"},"lv":{"language":"lv","value":"Itakeperika"},"pt-br":{"language":"pt-br","value":"Itapecerica da Serra"}},"descriptions":{"it":{"language":"it","value":"comune brasiliano"},"fr":{"language":"fr","value":"commune br\u00e9silienne"},"nl":{"language":"nl","value":"gemeente"},"en":{"language":"en","value":"municipality in the state of S\u00e3o Paulo in Brazil"},"es":{"language":"es","value":"municipio de la Microrregi\u00f3n de Itapecerica da Serra, en la Regi\u00f3n Metropolitana de S\u00e3o Paulo, estado de S\u00e3o Paulo, Brasil"},"pt":{"language":"pt","value":"munic\u00edpio no estado de S\u00e3o Paulo, no Brasil"},"de":{"language":"de","value":"Gemeinde im Bundesstaat S\u00e3o Paulo, Brasilien"},"nb":{"language":"nb","value":"kommune i S\u00e3o Paulo, Brasil"},"he":{"language":"he","value":"\u05e2\u05d9\u05e8 \u05d1\u05d1\u05e8\u05d6\u05d9\u05dc"},"hu":{"language":"hu","value":"k\u00f6zs\u00e9g Braz\u00edli\u00e1ban"},"pt-br":{"language":"pt-br","value":"munic\u00edpio do Estado de S\u00e3o Paulo"}},"aliases":{"pt":[{"language":"pt","value":"Itapecirica da Serra"}]},"claims":{"P373":[{"mainsnak":{"snaktype":"value","property":"P373","hash":"0adb7a50eca55ed9f7326e15ad0e3e16b7e4056b","datavalue":{"value":"Itapecerica da Serra","type":"string"},"datatype":"string"},"type":"statement","id":"q926662$F8490B1A-1752-44C1-B5F5-384864C69778","rank":"normal","references":[{"hash":"9a24f7c0208b05d6be97077d855671d1dfdbc0dd","snaks":{"P143":[{"snaktype":"value","property":"P143","hash":"d38375ffe6fe142663ff55cd783aa4df4301d83d","datavalue":{"value":{"entity-type":"item","numeric-id":48183,"id":"Q48183"},"type":"wikibase-entityid"},"datatype":"wikibase-item"}]},"snaks-order":["P143"]}]}],"P41":[{"mainsnak":{"snaktype":"value","property":"P41","hash":"a99264937c1b3e9d351d90894a1fd0b64815f2af","datavalue":{"value":"Bandeira ItapecericadaSerra SaoPaulo Brasil.svg","type":"string"},"datatype":"commonsMedia"},"type":"statement","id":"q926662$ecd376aa-4a18-463f-3f9f-ee9cb77b47a1","rank":"normal"}],"P625":[{"mainsnak":{"snaktype":"value","property":"P625","hash":"9b1239f9b26c15c0f14d8e4f3508346eb7198d5e","datavalue":{"value":{"latitude":-23.717222222222,"longitude":-46.849444444444,"altitude":null,"precision":null,"globe":"http://www.wikidata.org/entity/Q2"},"type":"globecoordinate"},"datatype":"globe-coordinate"},"type":"statement","id":"q926662$18147917-FC0F-41AA-BCD4-4FCF7FE5ADA7","rank":"normal"}],"P17":[{"mainsnak":{"snaktype":"value","property":"P17","hash":"90114304161d20f1934075ea47b8a33a76e95138","datavalue":{"value":{"entity-type":"item","numeric-id":155,"id":"Q155"},"type":"wikibase-entityid"},"datatype":"wikibase-item"},"type":"statement","id":"q926662$705E631D-53CE-4F47-9C85-4C3A167FB586","rank":"normal","references":[{"hash":"288ab581e7d2d02995a26dfa8b091d96e78457fc","snaks":{"P143":[{"snaktype":"value","property":"P143","hash":"6a164248fc96bfa583bbb495cb63ae6401ec203c","datavalue":{"value":{"entity-type":"item","numeric-id":206855,"id":"Q206855"},"type":"wikibase-entityid"},"datatype":"wikibase-item"}]},"snaks-order":["P143"]}]}],"P646":[{"mainsnak":{"snaktype":"value","property":"P646","hash":"634b76f50a840540b2e1b544039971001ede94d4","datavalue":{"value":"/m/041349","type":"string"},"datatype":"external-id"},"type":"statement","id":"Q926662$EA885E4D-3A5D-4B94-B406-03BE79EC972D","rank":"normal","references":[{"hash":"2b00cb481cddcac7623114367489b5c194901c4a","snaks":{"P248":[{"snaktype":"value","property":"P248","hash":"a94b740202b097dd33355e0e6c00e54b9395e5e0","datavalue":{"value":{"entity-type":"item","numeric-id":15241312,"id":"Q15241312"},"type":"wikibase-entityid"},"datatype":"wikibase-item"}],"P577":[{"snaktype":"value","property":"P577","hash":"fde79ecb015112d2f29229ccc1ec514ed3e71fa2","datavalue":{"value":{"time":"+2013-10-28T00:00:00Z","timezone":0,"before":0,"after":0,"precision":11,"calendarmodel":"http://www.wikidata.org/entity/Q1985727"},"type":"time"},"datatype":"time"}]},"snaks-order":["P248","P577"]}]}],"P131":[{"mainsnak":{"snaktype":"value","property":"P131","hash":"366d92f4d577645388ac0fa2be5042857215737a","datavalue":{"value":{"entity-type":"item","numeric-id":175,"id":"Q175"},"type":"wikibase-entityid"},"datatype":"wikibase-item"},"type":"statement","id":"Q926662$D76186B3-458C-46BD-A3F0-D9B2D0E035E5","rank":"normal"}],"P31":[{"mainsnak":{"snaktype":"value","property":"P31","hash":"1d2d976b06b7bb208fadcff54975cc04295b93c0","datavalue":{"value":{"entity-type":"item","numeric-id":515,"id":"Q515"},"type":"wikibase-entityid"},"datatype":"wikibase-item"},"type":"statement","id":"Q926662$1E302C72-08A1-44FA-8D05-3581A57CE7D1","rank":"normal"},{"mainsnak":{"snaktype":"value","property":"P31","hash":"64451778649ababeb1433bba2b9dbc5079680041","datavalue":{"value":{"entity-type":"item","numeric-id":3184121,"id":"Q3184121"},"type":"wikibase-entityid"},"datatype":"wikibase-item"},"type":"statement","id":"Q926662$C596184F-35FA-44A5-A22F-7E616EE737CB","rank":"normal"}],"P1566":[{"mainsnak":{"snaktype":"value","property":"P1566","hash":"e90fae65950cd9748201c0555809e808304955ef","datavalue":{"value":"3460748","type":"string"},"datatype":"external-id"},"type":"statement","id":"Q926662$DC4124A9-C3B6-4A17-AE84-C9A44A21BF74","rank":"normal","references":[{"hash":"64133510dcdf15e7943de41e4835c673fc5d6fe4","snaks":{"P143":[{"snaktype":"value","property":"P143","hash":"3439bea208036ec33ec3fba8245410df3efb8044","datavalue":{"value":{"entity-type":"item","numeric-id":830106,"id":"Q830106"},"type":"wikibase-entityid"},"datatype":"wikibase-item"}]},"snaks-order":["P143"]}]}],"P910":[{"mainsnak":{"snaktype":"value","property":"P910","hash":"3d0598e73236e63bde1251ca50d442aa2723820f","datavalue":{"value":{"entity-type":"item","numeric-id":10238727,"id":"Q10238727"},"type":"wikibase-entityid"},"datatype":"wikibase-item"},"type":"statement","id":"Q926662$CCD786B0-890B-4BD2-998B-E52184309914","rank":"normal","references":[{"hash":"9424852ca7d9d48269148c57acbefacca1899882","snaks":{"P143":[{"snaktype":"value","property":"P143","hash":"b7f8bea3bb10c237323eb448dc4798948923bd5c","datavalue":{"value":{"entity-type":"item","numeric-id":11921,"id":"Q11921"},"type":"wikibase-entityid"},"datatype":"wikibase-item"}]},"snaks-order":["P143"]}]}],"P214":[{"mainsnak":{"snaktype":"value","property":"P214","hash":"dc51acbcd6eb11b6f6512714cd5bc2281ac84927","datavalue":{"value":"156162610","type":"string"},"datatype":"external-id"},"type":"statement","id":"Q926662$D26EDFB6-D20A-4FC6-AC63-967193DA1E77","rank":"normal","references":[{"hash":"ad3713df772ae88af6a7458d084a40ad20b226d6","snaks":{"P248":[{"snaktype":"value","property":"P248","hash":"6b7d4330c4aac4caec4ede9de0311ce273f88ecd","datavalue":{"value":{"entity-type":"item","numeric-id":54919,"id":"Q54919"},"type":"wikibase-entityid"},"datatype":"wikibase-item"}],"P813":[{"snaktype":"value","property":"P813","hash":"a00cc299e508357647636e29593b8ca3e534077d","datavalue":{"value":{"time":"+2015-08-06T00:00:00Z","timezone":0,"before":0,"after":0,"precision":11,"calendarmodel":"http://www.wikidata.org/entity/Q1985727"},"type":"time"},"datatype":"time"}]},"snaks-order":["P248","P813"]}]}],"P47":[{"mainsnak":{"snaktype":"value","property":"P47","hash":"1e595b2dacedb97ba569dcce578f50204d949cd3","datavalue":{"value":{"entity-type":"item","numeric-id":651860,"id":"Q651860"},"type":"wikibase-entityid"},"datatype":"wikibase-item"},"type":"statement","id":"Q926662$E5ED5DB0-0A10-4E99-868A-7787855B2904","rank":"normal","references":[{"hash":"fa278ebfc458360e5aed63d5058cca83c46134f1","snaks":{"P143":[{"snaktype":"value","property":"P143","hash":"e4f6d9441d0600513c4533c672b5ab472dc73694","datavalue":{"value":{"entity-type":"item","numeric-id":328,"id":"Q328"},"type":"wikibase-entityid"},"datatype":"wikibase-item"}]},"snaks-order":["P143"]}]},{"mainsnak":{"snaktype":"value","property":"P47","hash":"e22083752bf9e2dcd3856d20edc9e8b7a898ffd2","datavalue":{"value":{"entity-type":"item","numeric-id":174,"id":"Q174"},"type":"wikibase-entityid"},"datatype":"wikibase-item"},"type":"statement","id":"Q926662$7371907C-41F9-45E7-BE59-50BBF9CC65DB","rank":"normal"},{"mainsnak":{"snaktype":"value","property":"P47","hash":"b34449a8a0f742545b53b1bd7d2617df14da10d8","datavalue":{"value":{"entity-type":"item","numeric-id":1749956,"id":"Q1749956"},"type":"wikibase-entityid"},"datatype":"wikibase-item"},"type":"statement","id":"Q926662$54BAAB49-65D5-409A-906F-047E29B778F4","rank":"normal"}],"P1281":[{"mainsnak":{"snaktype":"value","property":"P1281","hash":"ef56b2e24b22db7811d1513f55d76a4818be1edb","datavalue":{"value":"455959","type":"string"},"datatype":"external-id"},"type":"statement","id":"Q926662$02A3FA43-5D07-477B-AD4A-C13F160F0D27","rank":"normal","references":[{"hash":"d4767d15e44afe8795350d71c4aaf13e1067eea5","snaks":{"P248":[{"snaktype":"value","property":"P248","hash":"17354015300275daf133e0956af3a9b170765a0f","datavalue":{"value":{"entity-type":"item","numeric-id":24010939,"id":"Q24010939"},"type":"wikibase-entityid"},"datatype":"wikibase-item"}]},"snaks-order":["P248"]}]}],"P1585":[{"mainsnak":{"snaktype":"value","property":"P1585","hash":"4f3f09116f50fba3c1c73c6fd0999ee939215cf1","datavalue":{"value":"3522208","type":"string"},"datatype":"external-id"},"type":"statement","id":"Q926662$2382DC28-4BA1-420D-AA9A-509288766735","rank":"normal","references":[{"hash":"8f6d2b4a0e3da23aca841c5dfe6b7ed894bd315a","snaks":{"P143":[{"snaktype":"value","property":"P143","hash":"c4cc8cf0417b27e19c135f9b4312453d668ab641","datavalue":{"value":{"entity-type":"item","numeric-id":191769,"id":"Q191769"},"type":"wikibase-entityid"},"datatype":"wikibase-item"}]},"snaks-order":["P143"]}]}],"P1082":[{"mainsnak":{"snaktype":"value","property":"P1082","hash":"89162be9534fc2c99ebf8d54a53fd0ef2ea51349","datavalue":{"value":{"amount":"+129685","unit":"1"},"type":"quantity"},"datatype":"quantity"},"type":"statement","qualifiers":{"P585":[{"snaktype":"value","property":"P585","hash":"af2e73803c1d4751904f5933cf592cc3a1247193","datavalue":{"value":{"time":"+2000-08-01T00:00:00Z","timezone":0,"before":0,"after":0,"precision":11,"calendarmodel":"http://www.wikidata.org/entity/Q1985727"},"type":"time"},"datatype":"time"}],"P459":[{"snaktype":"value","property":"P459","hash":"f34609d440cf44ebaa8a3e704c9369413240618c","datavalue":{"value":{"entity-type":"item","numeric-id":39825,"id":"Q39825"},"type":"wikibase-entityid"},"datatype":"wikibase-item"}]},"qualifiers-order":["P585","P459"],"id":"Q926662$4064878B-C469-4ABE-AAFC-EA91A72A054D","rank":"normal","references":[{"hash":"75ea867d1143b2bcc0c513aed09d0374b487c364","snaks":{"P813":[{"snaktype":"value","property":"P813","hash":"2161e01a82ec3b867ce0de62fbf2329949929d0e","datavalue":{"value":{"time":"+2016-06-04T00:00:00Z","timezone":0,"before":0,"after":0,"precision":11,"calendarmodel":"http://www.wikidata.org/entity/Q1985727"},"type":"time"},"datatype":"time"}],"P1476":[{"snaktype":"value","property":"P1476","hash":"cae3e8e20eafea47233a902d1d9162b1cd95b583","datavalue":{"value":{"text":"Population by municipality","language":"en"},"type":"monolingualtext"},"datatype":"monolingualtext"}],"P854":[{"snaktype":"value","property":"P854","hash":"099b4e1abd1057a11065eb89b0e2d13c78719a17","datavalue":{"value":"http://www.ibge.gov.br/english/estatistica/populacao/censo2010/primeiros_resultados/populacao_por_municipio_zip.shtm","type":"string"},"datatype":"url"}]},"snaks-order":["P813","P1476","P854"]}]},{"mainsnak":{"snaktype":"value","property":"P1082","hash":"e4f9d2b4a815287c23b8e68d91676b7cd17e214c","datavalue":{"value":{"amount":"+167236","unit":"1"},"type":"quantity"},"datatype":"quantity"},"type":"statement","qualifiers":{"P585":[{"snaktype":"value","property":"P585","hash":"a3f90942a5afb60867bda9b4d2ca87c7eca72fef","datavalue":{"value":{"time":"+2015-07-01T00:00:00Z","timezone":0,"before":0,"after":0,"precision":11,"calendarmodel":"http://www.wikidata.org/entity/Q1985727"},"type":"time"},"datatype":"time"}],"P459":[{"snaktype":"value","property":"P459","hash":"59e16663852542d613c363dbd575ca58fff3b6e7","datavalue":{"value":{"entity-type":"item","numeric-id":791801,"id":"Q791801"},"type":"wikibase-entityid"},"datatype":"wikibase-item"}]},"qualifiers-order":["P585","P459"],"id":"Q926662$55B056C2-37CB-4303-8AD7-88B2B78214E3","rank":"preferred","references":[{"hash":"27bcf891f0c568374e303f9ab79eff12390a759a","snaks":{"P813":[{"snaktype":"value","property":"P813","hash":"2161e01a82ec3b867ce0de62fbf2329949929d0e","datavalue":{"value":{"time":"+2016-06-04T00:00:00Z","timezone":0,"before":0,"after":0,"precision":11,"calendarmodel":"http://www.wikidata.org/entity/Q1985727"},"type":"time"},"datatype":"time"}],"P1476":[{"snaktype":"value","property":"P1476","hash":"6211f7c65c507368966cae57615f2399e03e7fcb","datavalue":{"value":{"text":"Population estimates for July 1st, 2015","language":"en"},"type":"monolingualtext"},"datatype":"monolingualtext"}],"P854":[{"snaktype":"value","property":"P854","hash":"7039b8102e8add31dcee6f7e352617ad6f27cd4c","datavalue":{"value":"http://www.ibge.gov.br/english/estatistica/populacao/estimativa2015/estimativa_tcu.shtm","type":"string"},"datatype":"url"}]},"snaks-order":["P813","P1476","P854"]}]},{"mainsnak":{"snaktype":"value","property":"P1082","hash":"3c12c606d0e257696d9425593c21a242d5a9b0d3","datavalue":{"value":{"amount":"+152614","unit":"1"},"type":"quantity"},"datatype":"quantity"},"type":"statement","qualifiers":{"P459":[{"snaktype":"value","property":"P459","hash":"f34609d440cf44ebaa8a3e704c9369413240618c","datavalue":{"value":{"entity-type":"item","numeric-id":39825,"id":"Q39825"},"type":"wikibase-entityid"},"datatype":"wikibase-item"}],"P585":[{"snaktype":"value","property":"P585","hash":"f685a3b38f035c344da64e6c1dc211dd86558ae5","datavalue":{"value":{"time":"+2010-01-01T00:00:00Z","timezone":0,"before":0,"after":0,"precision":9,"calendarmodel":"http://www.wikidata.org/entity/Q1985727"},"type":"time"},"datatype":"time"}]},"qualifiers-order":["P459","P585"],"id":"Q926662$459E8905-90C9-4003-8C5E-FACBADDA4C89","rank":"normal","references":[{"hash":"d6c455e1541d4d661e8b63a2d2dd7ce73dc60612","snaks":{"P248":[{"snaktype":"value","property":"P248","hash":"13063e8f1275e3730a3c967326b8760833635676","datavalue":{"value":{"entity-type":"item","numeric-id":4350750,"id":"Q4350750"},"type":"wikibase-entityid"},"datatype":"wikibase-item"}]},"snaks-order":["P248"]}]}],"P242":[{"mainsnak":{"snaktype":"value","property":"P242","hash":"dc786e2ba7499fe19d2fcb79ca6f04d1b719fb22","datavalue":{"value":"SaoPaulo Municip ItapecericadaSerra.svg","type":"string"},"datatype":"commonsMedia"},"type":"statement","id":"Q926662$31690E0A-E2FB-4494-8747-7DADBE0FEBA9","rank":"normal","references":[{"hash":"d4bd87b862b12d99d26e86472d44f26858dee639","snaks":{"P143":[{"snaktype":"value","property":"P143","hash":"f30cbd35620c4ea6d0633aaf0210a8916130469b","datavalue":{"value":{"entity-type":"item","numeric-id":8447,"id":"Q8447"},"type":"wikibase-entityid"},"datatype":"wikibase-item"}]},"snaks-order":["P143"]}]}],"P94":[{"mainsnak":{"snaktype":"value","property":"P94","hash":"4a8fa2722156382849696ce1df0c2c4dc6d85cf8","datavalue":{"value":"Bras\u00e3o de Itapecerica da Serra.jpg","type":"string"},"datatype":"commonsMedia"},"type":"statement","id":"Q926662$F5CDD011-6A5C-4D38-9D29-6F5EC4D9556A","rank":"normal","references":[{"hash":"288ab581e7d2d02995a26dfa8b091d96e78457fc","snaks":{"P143":[{"snaktype":"value","property":"P143","hash":"6a164248fc96bfa583bbb495cb63ae6401ec203c","datavalue":{"value":{"entity-type":"item","numeric-id":206855,"id":"Q206855"},"type":"wikibase-entityid"},"datatype":"wikibase-item"}]},"snaks-order":["P143"]}]}],"P2044":[{"mainsnak":{"snaktype":"value","property":"P2044","hash":"680751ad4f2b749d070a220171fe0c95dc61fb70","datavalue":{"value":{"amount":"+920","unit":"http://www.wikidata.org/entity/Q11573"},"type":"quantity"},"datatype":"quantity"},"type":"statement","id":"Q926662$CA9E8AE2-543D-415B-8EBF-8F96803D3CA0","rank":"normal","references":[{"hash":"c456dc5cd2117249948c288206ff3f8b1bf574f0","snaks":{"P143":[{"snaktype":"value","property":"P143","hash":"e17507043402fe54ae6c4d65cc51f46cec987de9","datavalue":{"value":{"entity-type":"item","numeric-id":8449,"id":"Q8449"},"type":"wikibase-entityid"},"datatype":"wikibase-item"}]},"snaks-order":["P143"]}]}],"P18":[{"mainsnak":{"snaktype":"value","property":"P18","hash":"bc940525d73d1bc8686d2c50af02a7f0ed1ee941","datavalue":{"value":"Igreja matriz de Itapecerica da Serra.jpg","type":"string"},"datatype":"commonsMedia"},"type":"statement","id":"Q926662$8E8B3D61-FA7E-4925-98C7-04B663A6510F","rank":"normal","references":[{"hash":"9424852ca7d9d48269148c57acbefacca1899882","snaks":{"P143":[{"snaktype":"value","property":"P143","hash":"b7f8bea3bb10c237323eb448dc4798948923bd5c","datavalue":{"value":{"entity-type":"item","numeric-id":11921,"id":"Q11921"},"type":"wikibase-entityid"},"datatype":"wikibase-item"}]},"snaks-order":["P143"]}]}],"P1081":[{"mainsnak":{"snaktype":"value","property":"P1081","hash":"84b8bf869e4240b22016e72084870b7186a17cb7","datavalue":{"value":{"amount":"+0.742","unit":"1"},"type":"quantity"},"datatype":"quantity"},"type":"statement","id":"Q926662$5759D0B8-656B-4D06-AA51-C66CB6D3493A","rank":"normal","references":[{"hash":"9424852ca7d9d48269148c57acbefacca1899882","snaks":{"P143":[{"snaktype":"value","property":"P143","hash":"b7f8bea3bb10c237323eb448dc4798948923bd5c","datavalue":{"value":{"entity-type":"item","numeric-id":11921,"id":"Q11921"},"type":"wikibase-entityid"},"datatype":"wikibase-item"}]},"snaks-order":["P143"]}]}],"P281":[{"mainsnak":{"snaktype":"value","property":"P281","hash":"acd6b6658aa27da48af88cfadf1dc1b36fb8e4ec","datavalue":{"value":"06850-000 at\u00e9 06889-999","type":"string"},"datatype":"string"},"type":"statement","id":"Q926662$367C95D3-DB91-46F4-A9A8-7DC4F75682C4","rank":"normal","references":[{"hash":"9424852ca7d9d48269148c57acbefacca1899882","snaks":{"P143":[{"snaktype":"value","property":"P143","hash":"b7f8bea3bb10c237323eb448dc4798948923bd5c","datavalue":{"value":{"entity-type":"item","numeric-id":11921,"id":"Q11921"},"type":"wikibase-entityid"},"datatype":"wikibase-item"}]},"snaks-order":["P143"]}]}],"P2046":[{"mainsnak":{"snaktype":"value","property":"P2046","hash":"9dc05b4cbda0fed849efa9c1dfd0ebc6d9217f40","datavalue":{"value":{"amount":"+151.458","unit":"http://www.wikidata.org/entity/Q712226"},"type":"quantity"},"datatype":"quantity"},"type":"statement","id":"Q926662$89FFEF5C-5528-4F9B-8E9A-30C799912FD5","rank":"normal","references":[{"hash":"9424852ca7d9d48269148c57acbefacca1899882","snaks":{"P143":[{"snaktype":"value","property":"P143","hash":"b7f8bea3bb10c237323eb448dc4798948923bd5c","datavalue":{"value":{"entity-type":"item","numeric-id":11921,"id":"Q11921"},"type":"wikibase-entityid"},"datatype":"wikibase-item"}]},"snaks-order":["P143"]}]}],"P982":[{"mainsnak":{"snaktype":"value","property":"P982","hash":"89d53e88b87fcf0e10c33990094c1c0eaf29826a","datavalue":{"value":"319f15db-dc21-40d0-9dd5-142d0b600c1c","type":"string"},"datatype":"external-id"},"type":"statement","id":"Q926662$E263AEE2-8B91-4114-856B-8072A99F5934","rank":"normal","references":[{"hash":"706208b3024200fd0a39ad499808dd0d98d74065","snaks":{"P248":[{"snaktype":"value","property":"P248","hash":"623cc8f0e2f65afe4d66b91962d354a2f3aa9a27","datavalue":{"value":{"entity-type":"item","numeric-id":14005,"id":"Q14005"},"type":"wikibase-entityid"},"datatype":"wikibase-item"}]},"snaks-order":["P248"]}]}]},"sitelinks":{"arwiki":{"site":"arwiki","title":"\u0625\u062a\u0627\u0628\u064a\u0633\u064a\u0631\u064a\u0643\u0627 \u062f\u0627 \u0633\u064a\u0631\u0627","badges":[]},"bpywiki":{"site":"bpywiki","title":"\u0987\u099f\u09be\u09aa\u09c7\u09b8\u09c7\u09b0\u09bf\u0995\u09be \u09a1\u09be \u09b8\u09c7\u09b0\u09cd\u09b0\u09be","badges":[]},"cebwiki":{"site":"cebwiki","title":"Itapecerica da Serra (lungsod)","badges":[]},"commonswiki":{"site":"commonswiki","title":"Category:Itapecerica da Serra","badges":[]},"dewiki":{"site":"dewiki","title":"Itapecerica da Serra","badges":[]},"enwiki":{"site":"enwiki","title":"Itapecerica da Serra","badges":[]},"enwikivoyage":{"site":"enwikivoyage","title":"Itapecerica da Serra","badges":[]},"eowiki":{"site":"eowiki","title":"Itapecerica da Serra","badges":[]},"eswiki":{"site":"eswiki","title":"Itapecerica da Serra","badges":[]},"euwiki":{"site":"euwiki","title":"Itapecerica da Serra","badges":[]},"frwiki":{"site":"frwiki","title":"Itapecerica da Serra","badges":[]},"itwiki":{"site":"itwiki","title":"Itapecerica da Serra","badges":[]},"kkwiki":{"site":"kkwiki","title":"\u0418\u0442\u0430\u043f\u0435\u0441\u0435\u0440\u0438\u043a\u0430-\u0434\u0430-\u0421\u0435\u0440\u0440\u0430","badges":[]},"mgwiki":{"site":"mgwiki","title":"Itapecerica da Serra","badges":[]},"nlwiki":{"site":"nlwiki","title":"Itapecerica da Serra (gemeente)","badges":[]},"nowiki":{"site":"nowiki","title":"Itapecerica da Serra","badges":[]},"plwiki":{"site":"plwiki","title":"Itapecerica da Serra","badges":[]},"ptwiki":{"site":"ptwiki","title":"Itapecerica da Serra","badges":[]},"ptwikivoyage":{"site":"ptwikivoyage","title":"Itapecerica da Serra","badges":[]},"rowiki":{"site":"rowiki","title":"Itapecerica da Serra","badges":[]},"ruwiki":{"site":"ruwiki","title":"\u0418\u0442\u0430\u043f\u0435\u0441\u0435\u0440\u0438\u043a\u0430-\u0434\u0430-\u0421\u0435\u0440\u0440\u0430","badges":[]},"svwiki":{"site":"svwiki","title":"Itapecerica da Serra","badges":[]},"ukwiki":{"site":"ukwiki","title":"\u0406\u0442\u0430\u043f\u0435\u0441\u0435\u0440\u0456\u043a\u0430-\u0434\u0430-\u0421\u0435\u0440\u0440\u0430","badges":[]},"viwiki":{"site":"viwiki","title":"Itapecerica da Serra","badges":[]},"vowiki":{"site":"vowiki","title":"Itapecerica da Serra","badges":[]},"warwiki":{"site":"warwiki","title":"Itapecerica da Serra","badges":[]},"zh_min_nanwiki":{"site":"zh_min_nanwiki","title":"Itapecerica da Serra","badges":[]},"zhwiki":{"site":"zhwiki","title":"\u4f0a\u5854\u4f69\u585e\u91cc\u5361-\u8fbe\u585e\u62c9","badges":[]}}}},"success":1}