{
    "pageid": 1739615,
    "ns": 0,
    "type": "item",
    "id": "Q1808440",
    "claims": {
        "P625": [
            {
                "value": {
                    "latitude": -7.5458333333333,
                    "longitude": -72.583888888889,
                    "altitude": null,
                    "precision": 0.00027777777777778,
                    "globe": "http://www.wikidata.org/entity/Q2"
                },
                "type": "globecoordinate"
            }
        ],
        "P17": [
            {
                "value": {
                    "entity-type": "item",
                    "numeric-id": 155,
                    "id": "Q155"
                },
                "type": "wikibase-entityid"
            }
        ],
        "P131": [
            {
                "value": {
                    "entity-type": "item",
                    "numeric-id": 40040,
                    "id": "Q40040"
                },
                "type": "wikibase-entityid"
            }
        ],
        "P31": [
            {
                "value": {
                    "entity-type": "item",
                    "numeric-id": 3184121,
                    "id": "Q3184121"
                },
                "type": "wikibase-entityid"
            }
        ],
        "P646": [
            {
                "value": "/m/026x13v",
                "type": "string"
            }
        ],
        "P1566": [
            {
                "value": "3663973",
                "type": "string"
            }
        ],
        "P373": [
            {
                "value": "Guajará",
                "type": "string"
            }
        ],
        "P856": [
            {
                "value": "http://guajara.am.gov.br",
                "type": "string"
            }
        ],
        "P1585": [
            {
                "value": "1301654",
                "type": "string"
            }
        ],
        "P1082": [
            {
                "value": {
                    "amount": "+13220",
                    "unit": "1"
                },
                "type": "quantity"
            },
            {
                "value": {
                    "amount": "+15826",
                    "unit": "1"
                },
                "type": "quantity"
            },
            {
                "value": {
                    "amount": "+13974",
                    "unit": "1"
                },
                "type": "quantity"
            }
        ],
        "P242": [
            {
                "value": "Amazonas Municip Guajara.jpg",
                "type": "string"
            }
        ],
        "P41": [
            {
                "value": "Bandeira de Guajará AM.svg",
                "type": "string"
            }
        ],
        "P2046": [
            {
                "value": {
                    "amount": "+7578.876",
                    "unit": "http://www.wikidata.org/entity/Q712226"
                },
                "type": "quantity"
            }
        ],
        "P1081": [
            {
                "value": {
                    "amount": "+0.532",
                    "unit": "1"
                },
                "type": "quantity"
            }
        ],
        "P47": [
            {
                "value": {
                    "entity-type": "item",
                    "numeric-id": 1793319,
                    "id": "Q1793319"
                },
                "type": "wikibase-entityid"
            },
            {
                "value": {
                    "entity-type": "item",
                    "numeric-id": 1794374,
                    "id": "Q1794374"
                },
                "type": "wikibase-entityid"
            },
            {
                "value": {
                    "entity-type": "item",
                    "numeric-id": 1772621,
                    "id": "Q1772621"
                },
                "type": "wikibase-entityid"
            },
            {
                "value": {
                    "entity-type": "item",
                    "numeric-id": 941136,
                    "id": "Q941136"
                },
                "type": "wikibase-entityid"
            }
        ],
        "P402": [
            {
                "value": "332508",
                "type": "string"
            }
        ]
    }
}