{
    "pageid": 1734431,
    "ns": 0,
    "type": "item",
    "id": "Q1803204",
    "claims": {
        "P17": [
            {
                "value": {
                    "entity-type": "item",
                    "numeric-id": 155,
                    "id": "Q155"
                },
                "type": "wikibase-entityid"
            }
        ],
        "P625": [
            {
                "value": {
                    "latitude": -28.818888888889,
                    "longitude": -53.386944444444,
                    "altitude": null,
                    "precision": 0.00027777777777778,
                    "globe": "http://www.wikidata.org/entity/Q2"
                },
                "type": "globecoordinate"
            }
        ],
        "P131": [
            {
                "value": {
                    "entity-type": "item",
                    "numeric-id": 40030,
                    "id": "Q40030"
                },
                "type": "wikibase-entityid"
            }
        ],
        "P31": [
            {
                "value": {
                    "entity-type": "item",
                    "numeric-id": 3184121,
                    "id": "Q3184121"
                },
                "type": "wikibase-entityid"
            }
        ],
        "P373": [
            {
                "value": "Boa Vista do Incra",
                "type": "string"
            }
        ],
        "P94": [
            {
                "value": "Brasão Boa Vista do Incra.jpg",
                "type": "string"
            }
        ],
        "P41": [
            {
                "value": "Bandeira Boa Vista do Incra.JPG",
                "type": "string"
            }
        ],
        "P1566": [
            {
                "value": "6324127",
                "type": "string"
            }
        ],
        "P1585": [
            {
                "value": "4302238",
                "type": "string"
            }
        ],
        "P1082": [
            {
                "value": {
                    "amount": "+2425",
                    "unit": "1"
                },
                "type": "quantity"
            }
        ],
        "P242": [
            {
                "value": "Locator map of Boa Vista do Incra in Rio Grande do Sul.svg",
                "type": "string"
            }
        ],
        "P2044": [
            {
                "value": {
                    "amount": "+409",
                    "unit": "http://www.wikidata.org/entity/Q11573"
                },
                "type": "quantity"
            }
        ],
        "P2046": [
            {
                "value": {
                    "amount": "+503.475",
                    "unit": "http://www.wikidata.org/entity/Q712226"
                },
                "type": "quantity"
            }
        ],
        "P47": [
            {
                "value": {
                    "entity-type": "item",
                    "numeric-id": 985966,
                    "id": "Q985966"
                },
                "type": "wikibase-entityid"
            }
        ],
        "P402": [
            {
                "value": "242466",
                "type": "string"
            }
        ],
        "P473": [
            {
                "value": "55",
                "type": "string"
            }
        ],
        "P856": [
            {
                "value": "http://www.boavistadoincra.rs.gov.br",
                "type": "string"
            }
        ],
        "P6555": [
            {
                "value": "89060",
                "type": "string"
            }
        ],
        "P3722": [
            {
                "value": "Maps of Boa Vista do Incra",
                "type": "string"
            }
        ],
        "P6766": [
            {
                "value": "101958973",
                "type": "string"
            }
        ]
    }
}