{
    "pageid": 725836,
    "ns": 0,
    "type": "item",
    "id": "Q772563",
    "claims": {
        "P41": [
            {
                "value": "Bandeira Caracarai.jpg",
                "type": "string"
            }
        ],
        "P158": [
            {
                "value": "Brasao Caracarai.jpg",
                "type": "string"
            }
        ],
        "P17": [
            {
                "value": {
                    "entity-type": "item",
                    "numeric-id": 155,
                    "id": "Q155"
                },
                "type": "wikibase-entityid"
            }
        ],
        "P94": [
            {
                "value": "Brasao Caracarai.jpg",
                "type": "string"
            }
        ],
        "P625": [
            {
                "value": {
                    "latitude": 1.8158333333333,
                    "longitude": -61.127777777778,
                    "altitude": null,
                    "precision": 0.00027777777777778,
                    "globe": "http://www.wikidata.org/entity/Q2"
                },
                "type": "globecoordinate"
            }
        ],
        "P373": [
            {
                "value": "Caracaraí",
                "type": "string"
            }
        ],
        "P131": [
            {
                "value": {
                    "entity-type": "item",
                    "numeric-id": 42508,
                    "id": "Q42508"
                },
                "type": "wikibase-entityid"
            }
        ],
        "P31": [
            {
                "value": {
                    "entity-type": "item",
                    "numeric-id": 3184121,
                    "id": "Q3184121"
                },
                "type": "wikibase-entityid"
            }
        ],
        "P646": [
            {
                "value": "/m/026cdqb",
                "type": "string"
            }
        ],
        "P1566": [
            {
                "value": "3664684",
                "type": "string"
            }
        ],
        "P910": [
            {
                "value": {
                    "entity-type": "item",
                    "numeric-id": 9588887,
                    "id": "Q9588887"
                },
                "type": "wikibase-entityid"
            }
        ],
        "P2044": [
            {
                "value": {
                    "amount": "+52",
                    "unit": "http://www.wikidata.org/entity/Q11573",
                    "upperBound": "+53",
                    "lowerBound": "+51"
                },
                "type": "quantity"
            }
        ],
        "P18": [
            {
                "value": "Caracaraí, Roraima.JPG",
                "type": "string"
            }
        ],
        "P856": [
            {
                "value": "http://www.caracarai.rr.gov.br/",
                "type": "string"
            }
        ],
        "P1585": [
            {
                "value": "1400209",
                "type": "string"
            }
        ],
        "P1082": [
            {
                "value": {
                    "amount": "+20537",
                    "unit": "1"
                },
                "type": "quantity"
            }
        ],
        "P242": [
            {
                "value": "Roraima Municip Caracarai.svg",
                "type": "string"
            }
        ],
        "P473": [
            {
                "value": "95",
                "type": "string"
            }
        ],
        "P2046": [
            {
                "value": {
                    "amount": "+47410.891",
                    "unit": "http://www.wikidata.org/entity/Q712226"
                },
                "type": "quantity"
            }
        ],
        "P1081": [
            {
                "value": {
                    "amount": "+0.624",
                    "unit": "1"
                },
                "type": "quantity"
            }
        ],
        "P281": [
            {
                "value": "69360-000",
                "type": "string"
            }
        ],
        "P47": [
            {
                "value": {
                    "entity-type": "item",
                    "numeric-id": 1786374,
                    "id": "Q1786374"
                },
                "type": "wikibase-entityid"
            },
            {
                "value": {
                    "entity-type": "item",
                    "numeric-id": 748315,
                    "id": "Q748315"
                },
                "type": "wikibase-entityid"
            },
            {
                "value": {
                    "entity-type": "item",
                    "numeric-id": 1751337,
                    "id": "Q1751337"
                },
                "type": "wikibase-entityid"
            }
        ],
        "P402": [
            {
                "value": "326293",
                "type": "string"
            }
        ]
    }
}