{"entities":{"Q945061":{"pageid":895185,"ns":0,"title":"Q945061","lastrevid":681651892,"modified":"2018-05-19T18:59:20Z","type":"item","id":"Q945061","labels":{"es":{"language":"es","value":"Ilhabela"},"bpy":{"language":"bpy","value":"\u0987\u09b2\u09b9\u09be\u09ac\u09c7\u09b2\u09be"},"ca":{"language":"ca","value":"Ilhabela"},"de":{"language":"de","value":"Ilhabela"},"en":{"language":"en","value":"Ilhabela, S\u00e3o Paulo"},"eo":{"language":"eo","value":"Ilhabela"},"fr":{"language":"fr","value":"Ilhabela"},"it":{"language":"it","value":"Ilhabela"},"kk":{"language":"kk","value":"\u0418\u043b\u044c\u044f\u0431\u0435\u043b\u0430"},"mg":{"language":"mg","value":"Ilhabela"},"nl":{"language":"nl","value":"Ilhabela"},"pl":{"language":"pl","value":"Ilhabela"},"pt":{"language":"pt","value":"Ilhabela"},"ro":{"language":"ro","value":"Ilhabela"},"ru":{"language":"ru","value":"\u0418\u043b\u044c\u044f\u0431\u0435\u043b\u0430"},"sv":{"language":"sv","value":"Ilhabela"},"vo":{"language":"vo","value":"Ilhabela"},"war":{"language":"war","value":"Ilhabela, S\u00e3o Paulo"},"nb":{"language":"nb","value":"Ilhabela"},"zh":{"language":"zh","value":"\u4f0a\u5229\u4e9a\u8d1d\u62c9"},"pt-br":{"language":"pt-br","value":"Ilhabela"},"ceb":{"language":"ceb","value":"Ilhabela (kapital sa munisipyo)"},"nan":{"language":"nan","value":"Ilhabela"},"ja":{"language":"ja","value":"\u30a4\u30ea\u30e3\u30d9\u30e9"},"eu":{"language":"eu","value":"Ilhabela"},"he":{"language":"he","value":"\u05d0\u05d9\u05dc\u05d9\u05d0\u05d1\u05dc\u05d4"},"hu":{"language":"hu","value":"Ilhabela, S\u00e3o Paulo"}},"descriptions":{"it":{"language":"it","value":"comune brasiliano"},"fr":{"language":"fr","value":"commune br\u00e9silienne"},"nl":{"language":"nl","value":"gemeente in S\u00e3o Paulo"},"en":{"language":"en","value":"archipelago and city situated 4 miles off the coast of S\u00e3o Paulo state in Brazil"},"es":{"language":"es","value":"nombre de una isla y el \u00fanico municipio-archipi\u00e9lago brasile\u00f1o oc\u00e9anico"},"pt":{"language":"pt","value":"dos \u00fanicos munic\u00edpio\u2013arquip\u00e9lago marinho brasileiro e est\u00e1 localizado no litoral norte do estado de S\u00e3o Paulo, microrregi\u00e3o de Caraguatatuba"},"pt-br":{"language":"pt-br","value":"munic\u00edpio do Estado de S\u00e3o Paulo"},"de":{"language":"de","value":"Gemeinde im Bundesstaat S\u00e3o Paulo, Brasilien"},"nb":{"language":"nb","value":"kommune i S\u00e3o Paulo, Brasil"},"he":{"language":"he","value":"\u05e2\u05d9\u05e8 \u05d1\u05d1\u05e8\u05d6\u05d9\u05dc"},"hu":{"language":"hu","value":"k\u00f6zs\u00e9g Braz\u00edli\u00e1ban"}},"aliases":{"en":[{"language":"en","value":"Ilhabela"},{"language":"en","value":"Ilha de S\u00e3o Sebasti\u00e3o"}],"es":[{"language":"es","value":"S\u00e3o Sebasti\u00e3o"}]},"claims":{"P373":[{"mainsnak":{"snaktype":"value","property":"P373","hash":"5a80ed973e565bed01b0255981599335d3fe0749","datavalue":{"value":"Ilhabela","type":"string"},"datatype":"string"},"type":"statement","id":"q945061$976F60C0-6B31-48C5-9789-90D0057FF934","rank":"normal","references":[{"hash":"fa278ebfc458360e5aed63d5058cca83c46134f1","snaks":{"P143":[{"snaktype":"value","property":"P143","hash":"e4f6d9441d0600513c4533c672b5ab472dc73694","datavalue":{"value":{"entity-type":"item","numeric-id":328,"id":"Q328"},"type":"wikibase-entityid"},"datatype":"wikibase-item"}]},"snaks-order":["P143"]}]}],"P41":[{"mainsnak":{"snaktype":"value","property":"P41","hash":"2dc75ff69c592767fd1b6898a8b8a469689c64cc","datavalue":{"value":"Ilhabela bandeira.gif","type":"string"},"datatype":"commonsMedia"},"type":"statement","id":"q945061$9B11C666-59F3-46EA-AC31-8899213370B1","rank":"normal","references":[{"hash":"fa278ebfc458360e5aed63d5058cca83c46134f1","snaks":{"P143":[{"snaktype":"value","property":"P143","hash":"e4f6d9441d0600513c4533c672b5ab472dc73694","datavalue":{"value":{"entity-type":"item","numeric-id":328,"id":"Q328"},"type":"wikibase-entityid"},"datatype":"wikibase-item"}]},"snaks-order":["P143"]}]}],"P158":[{"mainsnak":{"snaktype":"value","property":"P158","hash":"f73c8160d39108cb2e07715355267b37b1417e40","datavalue":{"value":"Ilhabela brasao.gif","type":"string"},"datatype":"commonsMedia"},"type":"statement","id":"q945061$6971749A-BE00-4E6F-A584-A61D893AF0E6","rank":"normal","references":[{"hash":"fa278ebfc458360e5aed63d5058cca83c46134f1","snaks":{"P143":[{"snaktype":"value","property":"P143","hash":"e4f6d9441d0600513c4533c672b5ab472dc73694","datavalue":{"value":{"entity-type":"item","numeric-id":328,"id":"Q328"},"type":"wikibase-entityid"},"datatype":"wikibase-item"}]},"snaks-order":["P143"]}]}],"P17":[{"mainsnak":{"snaktype":"value","property":"P17","hash":"90114304161d20f1934075ea47b8a33a76e95138","datavalue":{"value":{"entity-type":"item","numeric-id":155,"id":"Q155"},"type":"wikibase-entityid"},"datatype":"wikibase-item"},"type":"statement","id":"q945061$B491E171-AA2A-4EA3-BB4A-9F980F9B3361","rank":"normal","references":[{"hash":"fa278ebfc458360e5aed63d5058cca83c46134f1","snaks":{"P143":[{"snaktype":"value","property":"P143","hash":"e4f6d9441d0600513c4533c672b5ab472dc73694","datavalue":{"value":{"entity-type":"item","numeric-id":328,"id":"Q328"},"type":"wikibase-entityid"},"datatype":"wikibase-item"}]},"snaks-order":["P143"]}]}],"P625":[{"mainsnak":{"snaktype":"value","property":"P625","hash":"24c5a59681ec528ddf7a7759fc527c1f9a879c7d","datavalue":{"value":{"latitude":-23.777777777778,"longitude":-45.357777777778,"altitude":null,"precision":0.00027777777777778,"globe":"http://www.wikidata.org/entity/Q2"},"type":"globecoordinate"},"datatype":"globe-coordinate"},"type":"statement","id":"q945061$2776B9C8-BAAB-4FF7-B0FC-69AA900B5328","rank":"normal","references":[{"hash":"288ab581e7d2d02995a26dfa8b091d96e78457fc","snaks":{"P143":[{"snaktype":"value","property":"P143","hash":"6a164248fc96bfa583bbb495cb63ae6401ec203c","datavalue":{"value":{"entity-type":"item","numeric-id":206855,"id":"Q206855"},"type":"wikibase-entityid"},"datatype":"wikibase-item"}]},"snaks-order":["P143"]}]}],"P646":[{"mainsnak":{"snaktype":"value","property":"P646","hash":"f687516ee48cbdc5e1548a9e028257e4717971cd","datavalue":{"value":"/m/02yf9p","type":"string"},"datatype":"external-id"},"type":"statement","id":"Q945061$12BE4E0C-E909-4F6B-81F4-6861ED689E5C","rank":"normal","references":[{"hash":"2b00cb481cddcac7623114367489b5c194901c4a","snaks":{"P248":[{"snaktype":"value","property":"P248","hash":"a94b740202b097dd33355e0e6c00e54b9395e5e0","datavalue":{"value":{"entity-type":"item","numeric-id":15241312,"id":"Q15241312"},"type":"wikibase-entityid"},"datatype":"wikibase-item"}],"P577":[{"snaktype":"value","property":"P577","hash":"fde79ecb015112d2f29229ccc1ec514ed3e71fa2","datavalue":{"value":{"time":"+2013-10-28T00:00:00Z","timezone":0,"before":0,"after":0,"precision":11,"calendarmodel":"http://www.wikidata.org/entity/Q1985727"},"type":"time"},"datatype":"time"}]},"snaks-order":["P248","P577"]}]}],"P131":[{"mainsnak":{"snaktype":"value","property":"P131","hash":"366d92f4d577645388ac0fa2be5042857215737a","datavalue":{"value":{"entity-type":"item","numeric-id":175,"id":"Q175"},"type":"wikibase-entityid"},"datatype":"wikibase-item"},"type":"statement","id":"Q945061$74489F9F-D32C-4DBE-AF2F-F4D55B77D1C5","rank":"normal"}],"P31":[{"mainsnak":{"snaktype":"value","property":"P31","hash":"1d2d976b06b7bb208fadcff54975cc04295b93c0","datavalue":{"value":{"entity-type":"item","numeric-id":515,"id":"Q515"},"type":"wikibase-entityid"},"datatype":"wikibase-item"},"type":"statement","id":"Q945061$175D43A2-FA8B-42DD-9C96-BB5C0E66A8A0","rank":"normal"},{"mainsnak":{"snaktype":"value","property":"P31","hash":"64451778649ababeb1433bba2b9dbc5079680041","datavalue":{"value":{"entity-type":"item","numeric-id":3184121,"id":"Q3184121"},"type":"wikibase-entityid"},"datatype":"wikibase-item"},"type":"statement","id":"Q945061$EBB26346-BF45-4CFE-A546-F10EC252C270","rank":"normal"}],"P18":[{"mainsnak":{"snaktype":"value","property":"P18","hash":"9117c77f9ffd5de7578e3a24652359616bf1264a","datavalue":{"value":"Ilha Bela 023.jpg","type":"string"},"datatype":"commonsMedia"},"type":"statement","id":"Q945061$52B3453A-C993-4F74-A805-3B3AC6C1D607","rank":"normal"},{"mainsnak":{"snaktype":"value","property":"P18","hash":"1929dcf1d12903a844c754d14b25edf075b7c6de","datavalue":{"value":"Ilha Bela 022.jpg","type":"string"},"datatype":"commonsMedia"},"type":"statement","id":"Q945061$9D02CDDF-2C1F-4C33-BA30-F0BE6DA99393","rank":"normal"}],"P1566":[{"mainsnak":{"snaktype":"value","property":"P1566","hash":"e14f64092714de2b02ee13aba36fa70fd58db63e","datavalue":{"value":"3461425","type":"string"},"datatype":"external-id"},"type":"statement","id":"Q945061$7DB5F670-BF3A-4EFA-A6FF-AFA17D23B455","rank":"normal","references":[{"hash":"64133510dcdf15e7943de41e4835c673fc5d6fe4","snaks":{"P143":[{"snaktype":"value","property":"P143","hash":"3439bea208036ec33ec3fba8245410df3efb8044","datavalue":{"value":{"entity-type":"item","numeric-id":830106,"id":"Q830106"},"type":"wikibase-entityid"},"datatype":"wikibase-item"}]},"snaks-order":["P143"]}]}],"P910":[{"mainsnak":{"snaktype":"value","property":"P910","hash":"0940314478ef4205a36c5791f5641e110aacd97d","datavalue":{"value":{"entity-type":"item","numeric-id":10181748,"id":"Q10181748"},"type":"wikibase-entityid"},"datatype":"wikibase-item"},"type":"statement","id":"Q945061$7EEAB29E-0406-4768-827A-1F6714C75C64","rank":"normal","references":[{"hash":"9424852ca7d9d48269148c57acbefacca1899882","snaks":{"P143":[{"snaktype":"value","property":"P143","hash":"b7f8bea3bb10c237323eb448dc4798948923bd5c","datavalue":{"value":{"entity-type":"item","numeric-id":11921,"id":"Q11921"},"type":"wikibase-entityid"},"datatype":"wikibase-item"}]},"snaks-order":["P143"]}]}],"P214":[{"mainsnak":{"snaktype":"value","property":"P214","hash":"1c145f7b3e15758ee0565a9ce985d23d127d78be","datavalue":{"value":"143091146","type":"string"},"datatype":"external-id"},"type":"statement","id":"Q945061$678AD51C-4526-46AB-BC6A-116D39E43AB2","rank":"normal","references":[{"hash":"ad3713df772ae88af6a7458d084a40ad20b226d6","snaks":{"P248":[{"snaktype":"value","property":"P248","hash":"6b7d4330c4aac4caec4ede9de0311ce273f88ecd","datavalue":{"value":{"entity-type":"item","numeric-id":54919,"id":"Q54919"},"type":"wikibase-entityid"},"datatype":"wikibase-item"}],"P813":[{"snaktype":"value","property":"P813","hash":"a00cc299e508357647636e29593b8ca3e534077d","datavalue":{"value":{"time":"+2015-08-06T00:00:00Z","timezone":0,"before":0,"after":0,"precision":11,"calendarmodel":"http://www.wikidata.org/entity/Q1985727"},"type":"time"},"datatype":"time"}]},"snaks-order":["P248","P813"]}]}],"P47":[{"mainsnak":{"snaktype":"value","property":"P47","hash":"0288cbfe416aae28cb1e7b4af435af124473a276","datavalue":{"value":{"entity-type":"item","numeric-id":983498,"id":"Q983498"},"type":"wikibase-entityid"},"datatype":"wikibase-item"},"type":"statement","id":"Q945061$F8449E31-FE26-4390-8199-9D30665D2861","rank":"normal","references":[{"hash":"fa278ebfc458360e5aed63d5058cca83c46134f1","snaks":{"P143":[{"snaktype":"value","property":"P143","hash":"e4f6d9441d0600513c4533c672b5ab472dc73694","datavalue":{"value":{"entity-type":"item","numeric-id":328,"id":"Q328"},"type":"wikibase-entityid"},"datatype":"wikibase-item"}]},"snaks-order":["P143"]}]}],"P935":[{"mainsnak":{"snaktype":"value","property":"P935","hash":"a0c239968e07848bce77db7b579afa083a19ee8e","datavalue":{"value":"Ilha Bela","type":"string"},"datatype":"string"},"type":"statement","id":"Q945061$2AC8EFC0-4532-4B5D-A6AC-627DCD8186B8","rank":"normal"}],"P1281":[{"mainsnak":{"snaktype":"value","property":"P1281","hash":"0057dd070c84388b5b464dba488af04bb9e80f3d","datavalue":{"value":"435450","type":"string"},"datatype":"external-id"},"type":"statement","id":"Q945061$E576D596-7CDF-4C20-9DB8-5BF1B54F5EFF","rank":"normal","references":[{"hash":"d4767d15e44afe8795350d71c4aaf13e1067eea5","snaks":{"P248":[{"snaktype":"value","property":"P248","hash":"17354015300275daf133e0956af3a9b170765a0f","datavalue":{"value":{"entity-type":"item","numeric-id":24010939,"id":"Q24010939"},"type":"wikibase-entityid"},"datatype":"wikibase-item"}]},"snaks-order":["P248"]}]}],"P856":[{"mainsnak":{"snaktype":"value","property":"P856","hash":"6cc9cebe1f59ebee30d278b497f2273dacf3ff09","datavalue":{"value":"http://www.ilhabela.sp.gov.br/portugues/","type":"string"},"datatype":"url"},"type":"statement","id":"Q945061$6AA76B1D-78DA-4036-A791-9F6B6B89B879","rank":"normal","references":[{"hash":"d5847b9b6032aa8b13dae3c2dfd9ed5d114d21b3","snaks":{"P143":[{"snaktype":"value","property":"P143","hash":"5a343e7e758a4282a01316d3e959b6e653b767fc","datavalue":{"value":{"entity-type":"item","numeric-id":11920,"id":"Q11920"},"type":"wikibase-entityid"},"datatype":"wikibase-item"}]},"snaks-order":["P143"]}]}],"P1585":[{"mainsnak":{"snaktype":"value","property":"P1585","hash":"9bcc98f9cd945178b312d94fcae3fb50de9e95f9","datavalue":{"value":"3520400","type":"string"},"datatype":"external-id"},"type":"statement","id":"Q945061$90FF249F-560C-4B0A-AE3E-37D22A71321A","rank":"normal","references":[{"hash":"8f6d2b4a0e3da23aca841c5dfe6b7ed894bd315a","snaks":{"P143":[{"snaktype":"value","property":"P143","hash":"c4cc8cf0417b27e19c135f9b4312453d668ab641","datavalue":{"value":{"entity-type":"item","numeric-id":191769,"id":"Q191769"},"type":"wikibase-entityid"},"datatype":"wikibase-item"}]},"snaks-order":["P143"]}]}],"P1082":[{"mainsnak":{"snaktype":"value","property":"P1082","hash":"67fb6cf975ce78fa6d8b82bdfc8b7a8e29eb3aa7","datavalue":{"value":{"amount":"+20836","unit":"1"},"type":"quantity"},"datatype":"quantity"},"type":"statement","qualifiers":{"P585":[{"snaktype":"value","property":"P585","hash":"af2e73803c1d4751904f5933cf592cc3a1247193","datavalue":{"value":{"time":"+2000-08-01T00:00:00Z","timezone":0,"before":0,"after":0,"precision":11,"calendarmodel":"http://www.wikidata.org/entity/Q1985727"},"type":"time"},"datatype":"time"}],"P459":[{"snaktype":"value","property":"P459","hash":"f34609d440cf44ebaa8a3e704c9369413240618c","datavalue":{"value":{"entity-type":"item","numeric-id":39825,"id":"Q39825"},"type":"wikibase-entityid"},"datatype":"wikibase-item"}]},"qualifiers-order":["P585","P459"],"id":"Q945061$3A7632FC-FD63-4C55-A633-A3E5F90FC1D1","rank":"normal","references":[{"hash":"75ea867d1143b2bcc0c513aed09d0374b487c364","snaks":{"P813":[{"snaktype":"value","property":"P813","hash":"2161e01a82ec3b867ce0de62fbf2329949929d0e","datavalue":{"value":{"time":"+2016-06-04T00:00:00Z","timezone":0,"before":0,"after":0,"precision":11,"calendarmodel":"http://www.wikidata.org/entity/Q1985727"},"type":"time"},"datatype":"time"}],"P1476":[{"snaktype":"value","property":"P1476","hash":"cae3e8e20eafea47233a902d1d9162b1cd95b583","datavalue":{"value":{"text":"Population by municipality","language":"en"},"type":"monolingualtext"},"datatype":"monolingualtext"}],"P854":[{"snaktype":"value","property":"P854","hash":"099b4e1abd1057a11065eb89b0e2d13c78719a17","datavalue":{"value":"http://www.ibge.gov.br/english/estatistica/populacao/censo2010/primeiros_resultados/populacao_por_municipio_zip.shtm","type":"string"},"datatype":"url"}]},"snaks-order":["P813","P1476","P854"]}]},{"mainsnak":{"snaktype":"value","property":"P1082","hash":"79086939e624fccd5bad5b037cd13bae49e51a45","datavalue":{"value":{"amount":"+32197","unit":"1"},"type":"quantity"},"datatype":"quantity"},"type":"statement","qualifiers":{"P585":[{"snaktype":"value","property":"P585","hash":"a3f90942a5afb60867bda9b4d2ca87c7eca72fef","datavalue":{"value":{"time":"+2015-07-01T00:00:00Z","timezone":0,"before":0,"after":0,"precision":11,"calendarmodel":"http://www.wikidata.org/entity/Q1985727"},"type":"time"},"datatype":"time"}],"P459":[{"snaktype":"value","property":"P459","hash":"59e16663852542d613c363dbd575ca58fff3b6e7","datavalue":{"value":{"entity-type":"item","numeric-id":791801,"id":"Q791801"},"type":"wikibase-entityid"},"datatype":"wikibase-item"}]},"qualifiers-order":["P585","P459"],"id":"Q945061$F2294E19-9BFC-4CF7-B4FB-46310B6FDD45","rank":"preferred","references":[{"hash":"27bcf891f0c568374e303f9ab79eff12390a759a","snaks":{"P813":[{"snaktype":"value","property":"P813","hash":"2161e01a82ec3b867ce0de62fbf2329949929d0e","datavalue":{"value":{"time":"+2016-06-04T00:00:00Z","timezone":0,"before":0,"after":0,"precision":11,"calendarmodel":"http://www.wikidata.org/entity/Q1985727"},"type":"time"},"datatype":"time"}],"P1476":[{"snaktype":"value","property":"P1476","hash":"6211f7c65c507368966cae57615f2399e03e7fcb","datavalue":{"value":{"text":"Population estimates for July 1st, 2015","language":"en"},"type":"monolingualtext"},"datatype":"monolingualtext"}],"P854":[{"snaktype":"value","property":"P854","hash":"7039b8102e8add31dcee6f7e352617ad6f27cd4c","datavalue":{"value":"http://www.ibge.gov.br/english/estatistica/populacao/estimativa2015/estimativa_tcu.shtm","type":"string"},"datatype":"url"}]},"snaks-order":["P813","P1476","P854"]}]},{"mainsnak":{"snaktype":"value","property":"P1082","hash":"31bda89415939041aa04607fb252847bf91ad1e2","datavalue":{"value":{"amount":"+28196","unit":"1"},"type":"quantity"},"datatype":"quantity"},"type":"statement","qualifiers":{"P459":[{"snaktype":"value","property":"P459","hash":"f34609d440cf44ebaa8a3e704c9369413240618c","datavalue":{"value":{"entity-type":"item","numeric-id":39825,"id":"Q39825"},"type":"wikibase-entityid"},"datatype":"wikibase-item"}],"P585":[{"snaktype":"value","property":"P585","hash":"f685a3b38f035c344da64e6c1dc211dd86558ae5","datavalue":{"value":{"time":"+2010-01-01T00:00:00Z","timezone":0,"before":0,"after":0,"precision":9,"calendarmodel":"http://www.wikidata.org/entity/Q1985727"},"type":"time"},"datatype":"time"}]},"qualifiers-order":["P459","P585"],"id":"Q945061$6DB6ED1E-D4A4-4AFE-8839-605BDD0ACAFA","rank":"normal","references":[{"hash":"d6c455e1541d4d661e8b63a2d2dd7ce73dc60612","snaks":{"P248":[{"snaktype":"value","property":"P248","hash":"13063e8f1275e3730a3c967326b8760833635676","datavalue":{"value":{"entity-type":"item","numeric-id":4350750,"id":"Q4350750"},"type":"wikibase-entityid"},"datatype":"wikibase-item"}]},"snaks-order":["P248"]}]}],"P242":[{"mainsnak":{"snaktype":"value","property":"P242","hash":"f615c4892d110c721fc862badbf9401318d73d9c","datavalue":{"value":"SaoPaulo Municip Ilhabela.svg","type":"string"},"datatype":"commonsMedia"},"type":"statement","id":"Q945061$34FAA2A7-DA77-4E77-B0C3-549DF824F302","rank":"normal","references":[{"hash":"fa278ebfc458360e5aed63d5058cca83c46134f1","snaks":{"P143":[{"snaktype":"value","property":"P143","hash":"e4f6d9441d0600513c4533c672b5ab472dc73694","datavalue":{"value":{"entity-type":"item","numeric-id":328,"id":"Q328"},"type":"wikibase-entityid"},"datatype":"wikibase-item"}]},"snaks-order":["P143"]}]}],"P94":[{"mainsnak":{"snaktype":"value","property":"P94","hash":"6a4e4f89dfbcd1ad93b5905d90ef789fa61697d2","datavalue":{"value":"Ilhabela brasao.gif","type":"string"},"datatype":"commonsMedia"},"type":"statement","id":"Q945061$E2A3B0BB-2BE3-4682-9C05-3F41BC80C239","rank":"normal","references":[{"hash":"288ab581e7d2d02995a26dfa8b091d96e78457fc","snaks":{"P143":[{"snaktype":"value","property":"P143","hash":"6a164248fc96bfa583bbb495cb63ae6401ec203c","datavalue":{"value":{"entity-type":"item","numeric-id":206855,"id":"Q206855"},"type":"wikibase-entityid"},"datatype":"wikibase-item"}]},"snaks-order":["P143"]}]}],"P281":[{"mainsnak":{"snaktype":"value","property":"P281","hash":"d6e48a1bb829fe55c892e8afdf8d2f1e4b9df598","datavalue":{"value":"11630-000","type":"string"},"datatype":"string"},"type":"statement","id":"Q945061$786A4FE5-5783-477E-916D-3477A7952BF4","rank":"normal","references":[{"hash":"fa278ebfc458360e5aed63d5058cca83c46134f1","snaks":{"P143":[{"snaktype":"value","property":"P143","hash":"e4f6d9441d0600513c4533c672b5ab472dc73694","datavalue":{"value":{"entity-type":"item","numeric-id":328,"id":"Q328"},"type":"wikibase-entityid"},"datatype":"wikibase-item"}]},"snaks-order":["P143"]}]}],"P3417":[{"mainsnak":{"snaktype":"value","property":"P3417","hash":"e955588d7f39a948f65dd6338c062e8f99d44d76","datavalue":{"value":"Ilhabela","type":"string"},"datatype":"external-id"},"type":"statement","id":"Q945061$36FF334C-59BA-4786-82C1-49D1A13E1AB9","rank":"normal","references":[{"hash":"d0b5b6346d38f7e212f576fec2c6692ef2b86e6a","snaks":{"P143":[{"snaktype":"value","property":"P143","hash":"34bf155bb9a56ad024ed0ea67b631a59af17fc38","datavalue":{"value":{"entity-type":"item","numeric-id":51711,"id":"Q51711"},"type":"wikibase-entityid"},"datatype":"wikibase-item"}]},"snaks-order":["P143"]}]}],"P2044":[{"mainsnak":{"snaktype":"value","property":"P2044","hash":"d662a215927e7c9b02283cd19a5b2d971a892eee","datavalue":{"value":{"amount":"+7","unit":"http://www.wikidata.org/entity/Q11573"},"type":"quantity"},"datatype":"quantity"},"type":"statement","id":"Q945061$2B72FF53-3932-433F-B23E-A3210C13D6B9","rank":"normal"}],"P2046":[{"mainsnak":{"snaktype":"value","property":"P2046","hash":"4b9e6b1886e8ad3e0463257825ef056e5d11e2a1","datavalue":{"value":{"amount":"+347.5","unit":"http://www.wikidata.org/entity/Q712226"},"type":"quantity"},"datatype":"quantity"},"type":"statement","id":"Q945061$C7B82AEA-D5B1-4AF1-9349-64785F3325B8","rank":"normal","references":[{"hash":"9424852ca7d9d48269148c57acbefacca1899882","snaks":{"P143":[{"snaktype":"value","property":"P143","hash":"b7f8bea3bb10c237323eb448dc4798948923bd5c","datavalue":{"value":{"entity-type":"item","numeric-id":11921,"id":"Q11921"},"type":"wikibase-entityid"},"datatype":"wikibase-item"}]},"snaks-order":["P143"]}]}],"P1081":[{"mainsnak":{"snaktype":"value","property":"P1081","hash":"e0171269e072feb2d74618a2f75d243eb0741c9b","datavalue":{"value":{"amount":"+0.756","unit":"1"},"type":"quantity"},"datatype":"quantity"},"type":"statement","id":"Q945061$8591E47D-55A2-49AC-B609-CF76BA168515","rank":"normal","references":[{"hash":"9424852ca7d9d48269148c57acbefacca1899882","snaks":{"P143":[{"snaktype":"value","property":"P143","hash":"b7f8bea3bb10c237323eb448dc4798948923bd5c","datavalue":{"value":{"entity-type":"item","numeric-id":11921,"id":"Q11921"},"type":"wikibase-entityid"},"datatype":"wikibase-item"}]},"snaks-order":["P143"]}]}]},"sitelinks":{"bpywiki":{"site":"bpywiki","title":"\u0987\u09b2\u09b9\u09be\u09ac\u09c7\u09b2\u09be","badges":[]},"cawiki":{"site":"cawiki","title":"Ilhabela","badges":[]},"cebwiki":{"site":"cebwiki","title":"Ilhabela (kapital sa munisipyo)","badges":[]},"commonswiki":{"site":"commonswiki","title":"Category:Ilhabela","badges":[]},"dewiki":{"site":"dewiki","title":"Ilhabela","badges":[]},"enwiki":{"site":"enwiki","title":"Ilhabela","badges":[]},"enwikivoyage":{"site":"enwikivoyage","title":"Ilhabela","badges":["Q17559452"]},"eowiki":{"site":"eowiki","title":"Ilhabela","badges":[]},"eswiki":{"site":"eswiki","title":"Ilhabela","badges":[]},"euwiki":{"site":"euwiki","title":"Ilhabela","badges":[]},"frwiki":{"site":"frwiki","title":"Ilhabela","badges":[]},"itwiki":{"site":"itwiki","title":"Ilhabela","badges":[]},"kkwiki":{"site":"kkwiki","title":"\u0418\u043b\u044c\u044f\u0431\u0435\u043b\u0430","badges":[]},"mgwiki":{"site":"mgwiki","title":"Ilhabela","badges":[]},"nlwiki":{"site":"nlwiki","title":"Ilhabela","badges":[]},"nowiki":{"site":"nowiki","title":"Ilhabela","badges":[]},"plwiki":{"site":"plwiki","title":"Ilhabela","badges":[]},"ptwiki":{"site":"ptwiki","title":"Ilhabela","badges":[]},"ptwikivoyage":{"site":"ptwikivoyage","title":"Ilhabela","badges":[]},"rowiki":{"site":"rowiki","title":"Ilhabela","badges":[]},"ruwiki":{"site":"ruwiki","title":"\u0418\u043b\u044c\u044f\u0431\u0435\u043b\u0430","badges":[]},"svwiki":{"site":"svwiki","title":"Ilhabela","badges":[]},"vowiki":{"site":"vowiki","title":"Ilhabela","badges":[]},"warwiki":{"site":"warwiki","title":"Ilhabela, S\u00e3o Paulo","badges":[]},"zh_min_nanwiki":{"site":"zh_min_nanwiki","title":"Ilhabela","badges":[]},"zhwiki":{"site":"zhwiki","title":"\u4f0a\u5229\u4e9a\u8d1d\u62c9","badges":[]}}}},"success":1}