{"entities":{"Q1772643":{"pageid":1704688,"ns":0,"title":"Q1772643","lastrevid":681487604,"modified":"2018-05-19T12:17:47Z","type":"item","id":"Q1772643","labels":{"pt":{"language":"pt","value":"Porto Ferreira"},"eo":{"language":"eo","value":"Porto Ferreira"},"pl":{"language":"pl","value":"Porto Ferreira"},"fr":{"language":"fr","value":"Porto Ferreira"},"ru":{"language":"ru","value":"\u041f\u043e\u0440\u0442\u0443-\u0424\u0435\u0440\u0440\u0435\u0439\u0440\u0430"},"es":{"language":"es","value":"Porto Ferreira"},"en":{"language":"en","value":"Porto Ferreira"},"vo":{"language":"vo","value":"Porto Ferreira"},"ro":{"language":"ro","value":"Porto Ferreira"},"it":{"language":"it","value":"Porto Ferreira"},"mg":{"language":"mg","value":"Porto Ferreira"},"war":{"language":"war","value":"Porto Ferreira"},"bpy":{"language":"bpy","value":"\u09aa\u09b0\u09cd\u099f\u09cb \u09ab\u09c7\u09b0\u09cd\u09b0\u09c7\u0987\u09b0\u09be"},"nl":{"language":"nl","value":"Porto Ferreira"},"kk-arab":{"language":"kk-arab","value":"\u067e\u0648\u0631\u062a\u06cb-\u0641\u06d5\u0631\u0631\u06d5\u064a\u0631\u0627"},"kk-cyrl":{"language":"kk-cyrl","value":"\u041f\u043e\u0440\u0442\u0443-\u0424\u0435\u0440\u0440\u0435\u0439\u0440\u0430"},"kk-latn":{"language":"kk-latn","value":"Portw-Ferre\u00fdra"},"nb":{"language":"nb","value":"Porto Ferreira"},"kk":{"language":"kk","value":"\u041f\u043e\u0440\u0442\u0443-\u0424\u0435\u0440\u0440\u0435\u0439\u0440\u0430"},"zh":{"language":"zh","value":"\u8d39\u96f7\u62c9\u6e2f"},"de":{"language":"de","value":"Porto Ferreira"},"sv":{"language":"sv","value":"Porto Ferreira"},"ceb":{"language":"ceb","value":"Porto Ferreira"},"nan":{"language":"nan","value":"Porto Ferreira"},"eu":{"language":"eu","value":"Porto Ferreira"},"hu":{"language":"hu","value":"Porto Ferreira"},"pt-br":{"language":"pt-br","value":"Porto Ferreira"}},"descriptions":{"it":{"language":"it","value":"comune brasiliano"},"fr":{"language":"fr","value":"commune br\u00e9silienne"},"en":{"language":"en","value":"municipality in the state of S\u00e3o Paulo in Brazil"},"es":{"language":"es","value":"municipio brasile\u00f1o del estado de S\u00e3o Paulo"},"pt":{"language":"pt","value":"munic\u00edpio brasileiro do estado de S\u00e3o Paulo"},"de":{"language":"de","value":"Gemeinde im Bundesstaat S\u00e3o Paulo, Brasilien"},"nl":{"language":"nl","value":"stad in Brazili\u00eb"},"nb":{"language":"nb","value":"kommune i S\u00e3o Paulo, Brasil"},"sv":{"language":"sv","value":"ort"},"ceb":{"language":"ceb","value":"lungsod"},"he":{"language":"he","value":"\u05e2\u05d9\u05e8 \u05d1\u05d1\u05e8\u05d6\u05d9\u05dc"},"hu":{"language":"hu","value":"k\u00f6zs\u00e9g Braz\u00edli\u00e1ban"},"pt-br":{"language":"pt-br","value":"munic\u00edpio do Estado de S\u00e3o Paulo"}},"aliases":{},"claims":{"P17":[{"mainsnak":{"snaktype":"value","property":"P17","hash":"90114304161d20f1934075ea47b8a33a76e95138","datavalue":{"value":{"entity-type":"item","numeric-id":155,"id":"Q155"},"type":"wikibase-entityid"},"datatype":"wikibase-item"},"type":"statement","id":"q1772643$0A084043-B9F8-42C1-BF1B-EF7D796B5B14","rank":"normal","references":[{"hash":"fa278ebfc458360e5aed63d5058cca83c46134f1","snaks":{"P143":[{"snaktype":"value","property":"P143","hash":"e4f6d9441d0600513c4533c672b5ab472dc73694","datavalue":{"value":{"entity-type":"item","numeric-id":328,"id":"Q328"},"type":"wikibase-entityid"},"datatype":"wikibase-item"}]},"snaks-order":["P143"]}]}],"P94":[{"mainsnak":{"snaktype":"value","property":"P94","hash":"3561864fd77e0c0f161e2bdf1cc49f8e824fa8cb","datavalue":{"value":"Brasao pf.jpg","type":"string"},"datatype":"commonsMedia"},"type":"statement","id":"q1772643$D8AAECA8-1DD2-4DC3-8F63-85A83AE6E563","rank":"normal","references":[{"hash":"c456dc5cd2117249948c288206ff3f8b1bf574f0","snaks":{"P143":[{"snaktype":"value","property":"P143","hash":"e17507043402fe54ae6c4d65cc51f46cec987de9","datavalue":{"value":{"entity-type":"item","numeric-id":8449,"id":"Q8449"},"type":"wikibase-entityid"},"datatype":"wikibase-item"}]},"snaks-order":["P143"]}]}],"P625":[{"mainsnak":{"snaktype":"value","property":"P625","hash":"853174a9e101902bd1ba14f929fc416f81e1bbee","datavalue":{"value":{"latitude":-21.853888888889,"longitude":-47.478888888889,"altitude":null,"precision":0.00027777777777778,"globe":"http://www.wikidata.org/entity/Q2"},"type":"globecoordinate"},"datatype":"globe-coordinate"},"type":"statement","id":"q1772643$68C8D535-8BE2-45D4-81C9-708B313B42E8","rank":"normal","references":[{"hash":"288ab581e7d2d02995a26dfa8b091d96e78457fc","snaks":{"P143":[{"snaktype":"value","property":"P143","hash":"6a164248fc96bfa583bbb495cb63ae6401ec203c","datavalue":{"value":{"entity-type":"item","numeric-id":206855,"id":"Q206855"},"type":"wikibase-entityid"},"datatype":"wikibase-item"}]},"snaks-order":["P143"]}]}],"P646":[{"mainsnak":{"snaktype":"value","property":"P646","hash":"17381dc7adc49de0996dec1730ecbb175c6785d2","datavalue":{"value":"/m/0493mc","type":"string"},"datatype":"external-id"},"type":"statement","id":"Q1772643$C30DDA00-888C-4C68-91A3-BB78FDE1EFBE","rank":"normal","references":[{"hash":"2b00cb481cddcac7623114367489b5c194901c4a","snaks":{"P248":[{"snaktype":"value","property":"P248","hash":"a94b740202b097dd33355e0e6c00e54b9395e5e0","datavalue":{"value":{"entity-type":"item","numeric-id":15241312,"id":"Q15241312"},"type":"wikibase-entityid"},"datatype":"wikibase-item"}],"P577":[{"snaktype":"value","property":"P577","hash":"fde79ecb015112d2f29229ccc1ec514ed3e71fa2","datavalue":{"value":{"time":"+2013-10-28T00:00:00Z","timezone":0,"before":0,"after":0,"precision":11,"calendarmodel":"http://www.wikidata.org/entity/Q1985727"},"type":"time"},"datatype":"time"}]},"snaks-order":["P248","P577"]}]}],"P131":[{"mainsnak":{"snaktype":"value","property":"P131","hash":"366d92f4d577645388ac0fa2be5042857215737a","datavalue":{"value":{"entity-type":"item","numeric-id":175,"id":"Q175"},"type":"wikibase-entityid"},"datatype":"wikibase-item"},"type":"statement","id":"Q1772643$D70C95FE-93CE-460C-83D8-9BD6AD8A07A2","rank":"normal"}],"P31":[{"mainsnak":{"snaktype":"value","property":"P31","hash":"1d2d976b06b7bb208fadcff54975cc04295b93c0","datavalue":{"value":{"entity-type":"item","numeric-id":515,"id":"Q515"},"type":"wikibase-entityid"},"datatype":"wikibase-item"},"type":"statement","id":"Q1772643$ECC64AD2-F117-48EC-8AC6-EF080A98B101","rank":"normal"},{"mainsnak":{"snaktype":"value","property":"P31","hash":"64451778649ababeb1433bba2b9dbc5079680041","datavalue":{"value":{"entity-type":"item","numeric-id":3184121,"id":"Q3184121"},"type":"wikibase-entityid"},"datatype":"wikibase-item"},"type":"statement","id":"Q1772643$445FDA94-1D32-46F3-ABFF-C6A7BDD26705","rank":"normal"}],"P1566":[{"mainsnak":{"snaktype":"value","property":"P1566","hash":"090bc40754e7d4ada21eea5ea66af2d25f179c23","datavalue":{"value":"3452775","type":"string"},"datatype":"external-id"},"type":"statement","id":"Q1772643$B8A173C8-8DF8-4F4D-B27E-D3DF2C2B5C16","rank":"normal","references":[{"hash":"64133510dcdf15e7943de41e4835c673fc5d6fe4","snaks":{"P143":[{"snaktype":"value","property":"P143","hash":"3439bea208036ec33ec3fba8245410df3efb8044","datavalue":{"value":{"entity-type":"item","numeric-id":830106,"id":"Q830106"},"type":"wikibase-entityid"},"datatype":"wikibase-item"}]},"snaks-order":["P143"]}]}],"P373":[{"mainsnak":{"snaktype":"value","property":"P373","hash":"f9a5fd4884f3da9a52e3f2f4046919ad91ba2641","datavalue":{"value":"Porto Ferreira","type":"string"},"datatype":"string"},"type":"statement","id":"Q1772643$BEE46DC1-0E20-4163-8D8C-0403FAAEA92A","rank":"normal"}],"P1585":[{"mainsnak":{"snaktype":"value","property":"P1585","hash":"c35b8c1e647506a63041e2850aecfc5e77a18af2","datavalue":{"value":"3540705","type":"string"},"datatype":"external-id"},"type":"statement","id":"Q1772643$58CDD88E-0863-43C0-9E63-F205B385C543","rank":"normal","references":[{"hash":"8f6d2b4a0e3da23aca841c5dfe6b7ed894bd315a","snaks":{"P143":[{"snaktype":"value","property":"P143","hash":"c4cc8cf0417b27e19c135f9b4312453d668ab641","datavalue":{"value":{"entity-type":"item","numeric-id":191769,"id":"Q191769"},"type":"wikibase-entityid"},"datatype":"wikibase-item"}]},"snaks-order":["P143"]}]}],"P1082":[{"mainsnak":{"snaktype":"value","property":"P1082","hash":"76b477e13458ffa1702dc13221723206681afa21","datavalue":{"value":{"amount":"+47437","unit":"1"},"type":"quantity"},"datatype":"quantity"},"type":"statement","qualifiers":{"P585":[{"snaktype":"value","property":"P585","hash":"af2e73803c1d4751904f5933cf592cc3a1247193","datavalue":{"value":{"time":"+2000-08-01T00:00:00Z","timezone":0,"before":0,"after":0,"precision":11,"calendarmodel":"http://www.wikidata.org/entity/Q1985727"},"type":"time"},"datatype":"time"}],"P459":[{"snaktype":"value","property":"P459","hash":"f34609d440cf44ebaa8a3e704c9369413240618c","datavalue":{"value":{"entity-type":"item","numeric-id":39825,"id":"Q39825"},"type":"wikibase-entityid"},"datatype":"wikibase-item"}]},"qualifiers-order":["P585","P459"],"id":"Q1772643$6443B820-AC3C-4ADE-8336-DF81976DE30E","rank":"normal","references":[{"hash":"75ea867d1143b2bcc0c513aed09d0374b487c364","snaks":{"P813":[{"snaktype":"value","property":"P813","hash":"2161e01a82ec3b867ce0de62fbf2329949929d0e","datavalue":{"value":{"time":"+2016-06-04T00:00:00Z","timezone":0,"before":0,"after":0,"precision":11,"calendarmodel":"http://www.wikidata.org/entity/Q1985727"},"type":"time"},"datatype":"time"}],"P1476":[{"snaktype":"value","property":"P1476","hash":"cae3e8e20eafea47233a902d1d9162b1cd95b583","datavalue":{"value":{"text":"Population by municipality","language":"en"},"type":"monolingualtext"},"datatype":"monolingualtext"}],"P854":[{"snaktype":"value","property":"P854","hash":"099b4e1abd1057a11065eb89b0e2d13c78719a17","datavalue":{"value":"http://www.ibge.gov.br/english/estatistica/populacao/censo2010/primeiros_resultados/populacao_por_municipio_zip.shtm","type":"string"},"datatype":"url"}]},"snaks-order":["P813","P1476","P854"]}]},{"mainsnak":{"snaktype":"value","property":"P1082","hash":"0fe486faff174f0c312ca7ab2b02bb6f47cce965","datavalue":{"value":{"amount":"+54761","unit":"1"},"type":"quantity"},"datatype":"quantity"},"type":"statement","qualifiers":{"P585":[{"snaktype":"value","property":"P585","hash":"a3f90942a5afb60867bda9b4d2ca87c7eca72fef","datavalue":{"value":{"time":"+2015-07-01T00:00:00Z","timezone":0,"before":0,"after":0,"precision":11,"calendarmodel":"http://www.wikidata.org/entity/Q1985727"},"type":"time"},"datatype":"time"}],"P459":[{"snaktype":"value","property":"P459","hash":"59e16663852542d613c363dbd575ca58fff3b6e7","datavalue":{"value":{"entity-type":"item","numeric-id":791801,"id":"Q791801"},"type":"wikibase-entityid"},"datatype":"wikibase-item"}]},"qualifiers-order":["P585","P459"],"id":"Q1772643$586AEC90-EBB4-404D-8A74-C332E2F8F723","rank":"preferred","references":[{"hash":"27bcf891f0c568374e303f9ab79eff12390a759a","snaks":{"P813":[{"snaktype":"value","property":"P813","hash":"2161e01a82ec3b867ce0de62fbf2329949929d0e","datavalue":{"value":{"time":"+2016-06-04T00:00:00Z","timezone":0,"before":0,"after":0,"precision":11,"calendarmodel":"http://www.wikidata.org/entity/Q1985727"},"type":"time"},"datatype":"time"}],"P1476":[{"snaktype":"value","property":"P1476","hash":"6211f7c65c507368966cae57615f2399e03e7fcb","datavalue":{"value":{"text":"Population estimates for July 1st, 2015","language":"en"},"type":"monolingualtext"},"datatype":"monolingualtext"}],"P854":[{"snaktype":"value","property":"P854","hash":"7039b8102e8add31dcee6f7e352617ad6f27cd4c","datavalue":{"value":"http://www.ibge.gov.br/english/estatistica/populacao/estimativa2015/estimativa_tcu.shtm","type":"string"},"datatype":"url"}]},"snaks-order":["P813","P1476","P854"]}]},{"mainsnak":{"snaktype":"value","property":"P1082","hash":"426f5c9e6683436d53cd6c65db14484d197f00e9","datavalue":{"value":{"amount":"+51400","unit":"1"},"type":"quantity"},"datatype":"quantity"},"type":"statement","qualifiers":{"P459":[{"snaktype":"value","property":"P459","hash":"f34609d440cf44ebaa8a3e704c9369413240618c","datavalue":{"value":{"entity-type":"item","numeric-id":39825,"id":"Q39825"},"type":"wikibase-entityid"},"datatype":"wikibase-item"}],"P585":[{"snaktype":"value","property":"P585","hash":"f685a3b38f035c344da64e6c1dc211dd86558ae5","datavalue":{"value":{"time":"+2010-01-01T00:00:00Z","timezone":0,"before":0,"after":0,"precision":9,"calendarmodel":"http://www.wikidata.org/entity/Q1985727"},"type":"time"},"datatype":"time"}]},"qualifiers-order":["P459","P585"],"id":"Q1772643$1D1A2D5E-9685-427D-B5D2-163D45C46FB9","rank":"normal","references":[{"hash":"d6c455e1541d4d661e8b63a2d2dd7ce73dc60612","snaks":{"P248":[{"snaktype":"value","property":"P248","hash":"13063e8f1275e3730a3c967326b8760833635676","datavalue":{"value":{"entity-type":"item","numeric-id":4350750,"id":"Q4350750"},"type":"wikibase-entityid"},"datatype":"wikibase-item"}]},"snaks-order":["P248"]}]}],"P242":[{"mainsnak":{"snaktype":"value","property":"P242","hash":"09e5f83ea3596d10c99437394ad787faf30c6ff1","datavalue":{"value":"SaoPaulo Municip PortoFerreira.svg","type":"string"},"datatype":"commonsMedia"},"type":"statement","id":"Q1772643$BF312C56-7425-4A3A-8810-F28CB1072B52","rank":"normal","references":[{"hash":"d4bd87b862b12d99d26e86472d44f26858dee639","snaks":{"P143":[{"snaktype":"value","property":"P143","hash":"f30cbd35620c4ea6d0633aaf0210a8916130469b","datavalue":{"value":{"entity-type":"item","numeric-id":8447,"id":"Q8447"},"type":"wikibase-entityid"},"datatype":"wikibase-item"}]},"snaks-order":["P143"]}]}],"P856":[{"mainsnak":{"snaktype":"value","property":"P856","hash":"6ed0daf3890fd8a95981dd09a6ad5b8f544c5a47","datavalue":{"value":"http://www.portoferreira.sp.gov.br/","type":"string"},"datatype":"url"},"type":"statement","id":"Q1772643$B0944A14-FF2E-4B1C-AB52-B52ED7EB6C9A","rank":"normal","references":[{"hash":"d5847b9b6032aa8b13dae3c2dfd9ed5d114d21b3","snaks":{"P143":[{"snaktype":"value","property":"P143","hash":"5a343e7e758a4282a01316d3e959b6e653b767fc","datavalue":{"value":{"entity-type":"item","numeric-id":11920,"id":"Q11920"},"type":"wikibase-entityid"},"datatype":"wikibase-item"}]},"snaks-order":["P143"]}]}],"P2044":[{"mainsnak":{"snaktype":"value","property":"P2044","hash":"037b49bda990273f59b86919d10d1f9f93e1659e","datavalue":{"value":{"amount":"+549","unit":"http://www.wikidata.org/entity/Q11573"},"type":"quantity"},"datatype":"quantity"},"type":"statement","id":"Q1772643$FC3E0D6E-9AD1-4F38-BC76-F11F86CB0BCF","rank":"normal","references":[{"hash":"d5847b9b6032aa8b13dae3c2dfd9ed5d114d21b3","snaks":{"P143":[{"snaktype":"value","property":"P143","hash":"5a343e7e758a4282a01316d3e959b6e653b767fc","datavalue":{"value":{"entity-type":"item","numeric-id":11920,"id":"Q11920"},"type":"wikibase-entityid"},"datatype":"wikibase-item"}]},"snaks-order":["P143"]}]}],"P910":[{"mainsnak":{"snaktype":"value","property":"P910","hash":"e38225da2770b6ed0b4d696c3a6ec0e05b56f6e0","datavalue":{"value":{"entity-type":"item","numeric-id":27588850,"id":"Q27588850"},"type":"wikibase-entityid"},"datatype":"wikibase-item"},"type":"statement","id":"Q1772643$43FD8D5D-A91D-4A6E-B28A-666C61582D47","rank":"normal","references":[{"hash":"9424852ca7d9d48269148c57acbefacca1899882","snaks":{"P143":[{"snaktype":"value","property":"P143","hash":"b7f8bea3bb10c237323eb448dc4798948923bd5c","datavalue":{"value":{"entity-type":"item","numeric-id":11921,"id":"Q11921"},"type":"wikibase-entityid"},"datatype":"wikibase-item"}]},"snaks-order":["P143"]}]}],"P18":[{"mainsnak":{"snaktype":"value","property":"P18","hash":"30d7c85e78225b5aca55036baee961bb62069e9c","datavalue":{"value":"Porto Ferreira 002.jpg","type":"string"},"datatype":"commonsMedia"},"type":"statement","id":"Q1772643$C29F11F6-29E4-44A6-8EED-28FBB9B66F12","rank":"normal","references":[{"hash":"d5847b9b6032aa8b13dae3c2dfd9ed5d114d21b3","snaks":{"P143":[{"snaktype":"value","property":"P143","hash":"5a343e7e758a4282a01316d3e959b6e653b767fc","datavalue":{"value":{"entity-type":"item","numeric-id":11920,"id":"Q11920"},"type":"wikibase-entityid"},"datatype":"wikibase-item"}]},"snaks-order":["P143"]}]}],"P2046":[{"mainsnak":{"snaktype":"value","property":"P2046","hash":"dc68e7f46946083670447fcf57ad334e5179e195","datavalue":{"value":{"amount":"+243.906","unit":"http://www.wikidata.org/entity/Q712226"},"type":"quantity"},"datatype":"quantity"},"type":"statement","id":"Q1772643$0634C5BB-83BC-438E-83AB-7F3A58B5D60F","rank":"normal","references":[{"hash":"9424852ca7d9d48269148c57acbefacca1899882","snaks":{"P143":[{"snaktype":"value","property":"P143","hash":"b7f8bea3bb10c237323eb448dc4798948923bd5c","datavalue":{"value":{"entity-type":"item","numeric-id":11921,"id":"Q11921"},"type":"wikibase-entityid"},"datatype":"wikibase-item"}]},"snaks-order":["P143"]}]}],"P1081":[{"mainsnak":{"snaktype":"value","property":"P1081","hash":"5b52d4e93aae9bef7e50c42c0f111ef909af2dd7","datavalue":{"value":{"amount":"+0.751","unit":"1"},"type":"quantity"},"datatype":"quantity"},"type":"statement","id":"Q1772643$D6255954-876E-4E19-89DA-5389A9628772","rank":"normal","references":[{"hash":"9424852ca7d9d48269148c57acbefacca1899882","snaks":{"P143":[{"snaktype":"value","property":"P143","hash":"b7f8bea3bb10c237323eb448dc4798948923bd5c","datavalue":{"value":{"entity-type":"item","numeric-id":11921,"id":"Q11921"},"type":"wikibase-entityid"},"datatype":"wikibase-item"}]},"snaks-order":["P143"]}]}],"P47":[{"mainsnak":{"snaktype":"value","property":"P47","hash":"76eec2cc9eadd76177457570c1b631370ed5058b","datavalue":{"value":{"entity-type":"item","numeric-id":1649619,"id":"Q1649619"},"type":"wikibase-entityid"},"datatype":"wikibase-item"},"type":"statement","id":"Q1772643$8B13082D-D2A5-4287-9884-6F21E919CF6D","rank":"normal","references":[{"hash":"9424852ca7d9d48269148c57acbefacca1899882","snaks":{"P143":[{"snaktype":"value","property":"P143","hash":"b7f8bea3bb10c237323eb448dc4798948923bd5c","datavalue":{"value":{"entity-type":"item","numeric-id":11921,"id":"Q11921"},"type":"wikibase-entityid"},"datatype":"wikibase-item"}]},"snaks-order":["P143"]}]},{"mainsnak":{"snaktype":"value","property":"P47","hash":"bd883188efc2777f17ec3f71d3523a12f9891fb7","datavalue":{"value":{"entity-type":"item","numeric-id":1750431,"id":"Q1750431"},"type":"wikibase-entityid"},"datatype":"wikibase-item"},"type":"statement","id":"Q1772643$24DC35D6-9A81-4C93-ABF2-5846DA1EB0B9","rank":"normal"}],"P402":[{"mainsnak":{"snaktype":"value","property":"P402","hash":"253293c708fe26879d15151378c768a799ed5e17","datavalue":{"value":"298178","type":"string"},"datatype":"external-id"},"type":"statement","id":"Q1772643$6CE7F995-E4A5-4C35-B68A-B4F2D89CB1B5","rank":"normal"}]},"sitelinks":{"bpywiki":{"site":"bpywiki","title":"\u09aa\u09b0\u09cd\u099f\u09cb \u09ab\u09c7\u09b0\u09cd\u09b0\u09c7\u0987\u09b0\u09be","badges":[]},"cebwiki":{"site":"cebwiki","title":"Porto Ferreira (lungsod)","badges":[]},"commonswiki":{"site":"commonswiki","title":"Category:Porto Ferreira","badges":[]},"enwiki":{"site":"enwiki","title":"Porto Ferreira","badges":[]},"eowiki":{"site":"eowiki","title":"Porto Ferreira","badges":[]},"eswiki":{"site":"eswiki","title":"Porto Ferreira","badges":[]},"euwiki":{"site":"euwiki","title":"Porto Ferreira","badges":[]},"frwiki":{"site":"frwiki","title":"Porto Ferreira","badges":[]},"itwiki":{"site":"itwiki","title":"Porto Ferreira","badges":[]},"kkwiki":{"site":"kkwiki","title":"\u041f\u043e\u0440\u0442\u0443-\u0424\u0435\u0440\u0440\u0435\u0439\u0440\u0430","badges":[]},"mgwiki":{"site":"mgwiki","title":"Porto Ferreira","badges":[]},"nlwiki":{"site":"nlwiki","title":"Porto Ferreira","badges":[]},"nowiki":{"site":"nowiki","title":"Porto Ferreira","badges":[]},"plwiki":{"site":"plwiki","title":"Porto Ferreira","badges":[]},"ptwiki":{"site":"ptwiki","title":"Porto Ferreira","badges":[]},"ptwikivoyage":{"site":"ptwikivoyage","title":"Porto Ferreira","badges":[]},"rowiki":{"site":"rowiki","title":"Porto Ferreira","badges":[]},"ruwiki":{"site":"ruwiki","title":"\u041f\u043e\u0440\u0442\u0443-\u0424\u0435\u0440\u0440\u0435\u0439\u0440\u0430","badges":[]},"svwiki":{"site":"svwiki","title":"Porto Ferreira (ort)","badges":[]},"vowiki":{"site":"vowiki","title":"Porto Ferreira","badges":[]},"warwiki":{"site":"warwiki","title":"Porto Ferreira","badges":[]},"zh_min_nanwiki":{"site":"zh_min_nanwiki","title":"Porto Ferreira","badges":[]},"zhwiki":{"site":"zhwiki","title":"\u8d39\u96f7\u62c9\u6e2f","badges":[]}}}},"success":1}